[
  {
    "id": "47103505416",
    "type": "PushEvent",
    "actor": {
      "id": 102224869,
      "login": "Mwaldemar",
      "display_login": "Mwaldemar",
      "gravatar_id": "",
      "url": "https://api.github.com/users/Mwaldemar",
      "avatar_url": "https://avatars.githubusercontent.com/u/102224869?"
    },
    "repo": {
      "id": 925695263,
      "name": "Mwaldemar/Resume",
      "url": "https://api.github.com/repos/Mwaldemar/Resume"
    },
    "payload": {
      "repository_id": 925695263,
      "push_id": 22934687038,
      "size": 1,
      "distinct_size": 1,
      "ref": "refs/heads/main",
      "head": "0cc61a83fcd5087e567864ae3a016e99f041100d",
      "before": "a28b44c78c2c1296795c880498b2ec23b31fb5aa",
      "commits": [
        {
          "sha": "0cc61a83fcd5087e567864ae3a016e99f041100d",
          "author": {
            "email": "github-actions@github.com",
            "name": "GitHub Actions"
          },
          "message": "Update GitHub activity",
          "distinct": true,
          "url": "https://api.github.com/repos/Mwaldemar/Resume/commits/0cc61a83fcd5087e567864ae3a016e99f041100d"
        }
      ]
    },
    "public": true,
    "created_at": "2025-03-02T02:56:39Z"
  },
  {
    "id": "47102900284",
    "type": "PushEvent",
    "actor": {
      "id": 102224869,
      "login": "Mwaldemar",
      "display_login": "Mwaldemar",
      "gravatar_id": "",
      "url": "https://api.github.com/users/Mwaldemar",
      "avatar_url": "https://avatars.githubusercontent.com/u/102224869?"
    },
    "repo": {
      "id": 925695263,
      "name": "Mwaldemar/Resume",
      "url": "https://api.github.com/repos/Mwaldemar/Resume"
    },
    "payload": {
      "repository_id": 925695263,
      "push_id": 22934267395,
      "size": 1,
      "distinct_size": 1,
      "ref": "refs/heads/main",
      "head": "a28b44c78c2c1296795c880498b2ec23b31fb5aa",
      "before": "ff7804dae3b1c09cfe932ec4821e8a787db307c2",
      "commits": [
        {
          "sha": "a28b44c78c2c1296795c880498b2ec23b31fb5aa",
          "author": {
            "email": "github-actions@github.com",
            "name": "GitHub Actions"
          },
          "message": "Update GitHub activity",
          "distinct": true,
          "url": "https://api.github.com/repos/Mwaldemar/Resume/commits/a28b44c78c2c1296795c880498b2ec23b31fb5aa"
        }
      ]
    },
    "public": true,
    "created_at": "2025-03-02T01:41:52Z"
  },
  {
    "id": "47100582378",
    "type": "PushEvent",
    "actor": {
      "id": 102224869,
      "login": "Mwaldemar",
      "display_login": "Mwaldemar",
      "gravatar_id": "",
      "url": "https://api.github.com/users/Mwaldemar",
      "avatar_url": "https://avatars.githubusercontent.com/u/102224869?"
    },
    "repo": {
      "id": 925695263,
      "name": "Mwaldemar/Resume",
      "url": "https://api.github.com/repos/Mwaldemar/Resume"
    },
    "payload": {
      "repository_id": 925695263,
      "push_id": 22932667776,
      "size": 1,
      "distinct_size": 1,
      "ref": "refs/heads/main",
      "head": "ff7804dae3b1c09cfe932ec4821e8a787db307c2",
      "before": "7f204e53e6efe97a318bcca105e6aa561c2ce433",
      "commits": [
        {
          "sha": "ff7804dae3b1c09cfe932ec4821e8a787db307c2",
          "author": {
            "email": "github-actions@github.com",
            "name": "GitHub Actions"
          },
          "message": "Update GitHub activity",
          "distinct": true,
          "url": "https://api.github.com/repos/Mwaldemar/Resume/commits/ff7804dae3b1c09cfe932ec4821e8a787db307c2"
        }
      ]
    },
    "public": true,
    "created_at": "2025-03-01T21:17:22Z"
  },
  {
    "id": "47100004758",
    "type": "PushEvent",
    "actor": {
      "id": 102224869,
      "login": "Mwaldemar",
      "display_login": "Mwaldemar",
      "gravatar_id": "",
      "url": "https://api.github.com/users/Mwaldemar",
      "avatar_url": "https://avatars.githubusercontent.com/u/102224869?"
    },
    "repo": {
      "id": 925695263,
      "name": "Mwaldemar/Resume",
      "url": "https://api.github.com/repos/Mwaldemar/Resume"
    },
    "payload": {
      "repository_id": 925695263,
      "push_id": 22932275040,
      "size": 1,
      "distinct_size": 1,
      "ref": "refs/heads/main",
      "head": "7f204e53e6efe97a318bcca105e6aa561c2ce433",
      "before": "cef62e4efac13ac8bd805770e275b772c1ddd4eb",
      "commits": [
        {
          "sha": "7f204e53e6efe97a318bcca105e6aa561c2ce433",
          "author": {
            "email": "github-actions@github.com",
            "name": "GitHub Actions"
          },
          "message": "Update GitHub activity",
          "distinct": true,
          "url": "https://api.github.com/repos/Mwaldemar/Resume/commits/7f204e53e6efe97a318bcca105e6aa561c2ce433"
        }
      ]
    },
    "public": true,
    "created_at": "2025-03-01T20:19:38Z"
  },
  {
    "id": "47097964470",
    "type": "PushEvent",
    "actor": {
      "id": 102224869,
      "login": "Mwaldemar",
      "display_login": "Mwaldemar",
      "gravatar_id": "",
      "url": "https://api.github.com/users/Mwaldemar",
      "avatar_url": "https://avatars.githubusercontent.com/u/102224869?"
    },
    "repo": {
      "id": 925695263,
      "name": "Mwaldemar/Resume",
      "url": "https://api.github.com/repos/Mwaldemar/Resume"
    },
    "payload": {
      "repository_id": 925695263,
      "push_id": 22930879061,
      "size": 1,
      "distinct_size": 1,
      "ref": "refs/heads/main",
      "head": "cef62e4efac13ac8bd805770e275b772c1ddd4eb",
      "before": "457b7caa60dcb661ecb837c58631eb7700adb3b8",
      "commits": [
        {
          "sha": "cef62e4efac13ac8bd805770e275b772c1ddd4eb",
          "author": {
            "email": "github-actions@github.com",
            "name": "GitHub Actions"
          },
          "message": "Update GitHub activity",
          "distinct": true,
          "url": "https://api.github.com/repos/Mwaldemar/Resume/commits/cef62e4efac13ac8bd805770e275b772c1ddd4eb"
        }
      ]
    },
    "public": true,
    "created_at": "2025-03-01T17:16:03Z"
  },
  {
    "id": "47097209616",
    "type": "PushEvent",
    "actor": {
      "id": 102224869,
      "login": "Mwaldemar",
      "display_login": "Mwaldemar",
      "gravatar_id": "",
      "url": "https://api.github.com/users/Mwaldemar",
      "avatar_url": "https://avatars.githubusercontent.com/u/102224869?"
    },
    "repo": {
      "id": 925695263,
      "name": "Mwaldemar/Resume",
      "url": "https://api.github.com/repos/Mwaldemar/Resume"
    },
    "payload": {
      "repository_id": 925695263,
      "push_id": 22930369417,
      "size": 1,
      "distinct_size": 1,
      "ref": "refs/heads/main",
      "head": "457b7caa60dcb661ecb837c58631eb7700adb3b8",
      "before": "adb80a6f3034b16354dd0793882503dd88892d7c",
      "commits": [
        {
          "sha": "457b7caa60dcb661ecb837c58631eb7700adb3b8",
          "author": {
            "email": "github-actions@github.com",
            "name": "GitHub Actions"
          },
          "message": "Update GitHub repositories",
          "distinct": true,
          "url": "https://api.github.com/repos/Mwaldemar/Resume/commits/457b7caa60dcb661ecb837c58631eb7700adb3b8"
        }
      ]
    },
    "public": true,
    "created_at": "2025-03-01T16:10:22Z"
  },
  {
    "id": "47093879605",
    "type": "PushEvent",
    "actor": {
      "id": 102224869,
      "login": "Mwaldemar",
      "display_login": "Mwaldemar",
      "gravatar_id": "",
      "url": "https://api.github.com/users/Mwaldemar",
      "avatar_url": "https://avatars.githubusercontent.com/u/102224869?"
    },
    "repo": {
      "id": 925695263,
      "name": "Mwaldemar/Resume",
      "url": "https://api.github.com/repos/Mwaldemar/Resume"
    },
    "payload": {
      "repository_id": 925695263,
      "push_id": 22928125417,
      "size": 1,
      "distinct_size": 1,
      "ref": "refs/heads/main",
      "head": "adb80a6f3034b16354dd0793882503dd88892d7c",
      "before": "855cbdec6de8980d38c33553769ea391a790ccce",
      "commits": [
        {
          "sha": "adb80a6f3034b16354dd0793882503dd88892d7c",
          "author": {
            "email": "github-actions@github.com",
            "name": "GitHub Actions"
          },
          "message": "Update GitHub activity",
          "distinct": true,
          "url": "https://api.github.com/repos/Mwaldemar/Resume/commits/adb80a6f3034b16354dd0793882503dd88892d7c"
        }
      ]
    },
    "public": true,
    "created_at": "2025-03-01T11:14:52Z"
  },
  {
    "id": "47093266357",
    "type": "PushEvent",
    "actor": {
      "id": 102224869,
      "login": "Mwaldemar",
      "display_login": "Mwaldemar",
      "gravatar_id": "",
      "url": "https://api.github.com/users/Mwaldemar",
      "avatar_url": "https://avatars.githubusercontent.com/u/102224869?"
    },
    "repo": {
      "id": 925695263,
      "name": "Mwaldemar/Resume",
      "url": "https://api.github.com/repos/Mwaldemar/Resume"
    },
    "payload": {
      "repository_id": 925695263,
      "push_id": 22927714013,
      "size": 1,
      "distinct_size": 1,
      "ref": "refs/heads/main",
      "head": "855cbdec6de8980d38c33553769ea391a790ccce",
      "before": "b7a4aee414296a77c08ff119f03b59ba0da81763",
      "commits": [
        {
          "sha": "855cbdec6de8980d38c33553769ea391a790ccce",
          "author": {
            "email": "github-actions@github.com",
            "name": "GitHub Actions"
          },
          "message": "Update GitHub activity",
          "distinct": true,
          "url": "https://api.github.com/repos/Mwaldemar/Resume/commits/855cbdec6de8980d38c33553769ea391a790ccce"
        }
      ]
    },
    "public": true,
    "created_at": "2025-03-01T10:19:27Z"
  },
  {
    "id": "47083017273",
    "type": "PushEvent",
    "actor": {
      "id": 102224869,
      "login": "Mwaldemar",
      "display_login": "Mwaldemar",
      "gravatar_id": "",
      "url": "https://api.github.com/users/Mwaldemar",
      "avatar_url": "https://avatars.githubusercontent.com/u/102224869?"
    },
    "repo": {
      "id": 925695263,
      "name": "Mwaldemar/Resume",
      "url": "https://api.github.com/repos/Mwaldemar/Resume"
    },
    "payload": {
      "repository_id": 925695263,
      "push_id": 22921582681,
      "size": 1,
      "distinct_size": 1,
      "ref": "refs/heads/main",
      "head": "b7a4aee414296a77c08ff119f03b59ba0da81763",
      "before": "a1ca3fe7d784e3acd3fc9c9a24bacbbe000e25d8",
      "commits": [
        {
          "sha": "b7a4aee414296a77c08ff119f03b59ba0da81763",
          "author": {
            "email": "github-actions@github.com",
            "name": "GitHub Actions"
          },
          "message": "Update GitHub activity",
          "distinct": true,
          "url": "https://api.github.com/repos/Mwaldemar/Resume/commits/b7a4aee414296a77c08ff119f03b59ba0da81763"
        }
      ]
    },
    "public": true,
    "created_at": "2025-02-28T21:18:09Z"
  },
  {
    "id": "47081610342",
    "type": "PushEvent",
    "actor": {
      "id": 102224869,
      "login": "Mwaldemar",
      "display_login": "Mwaldemar",
      "gravatar_id": "",
      "url": "https://api.github.com/users/Mwaldemar",
      "avatar_url": "https://avatars.githubusercontent.com/u/102224869?"
    },
    "repo": {
      "id": 925695263,
      "name": "Mwaldemar/Resume",
      "url": "https://api.github.com/repos/Mwaldemar/Resume"
    },
    "payload": {
      "repository_id": 925695263,
      "push_id": 22920854186,
      "size": 1,
      "distinct_size": 1,
      "ref": "refs/heads/main",
      "head": "a1ca3fe7d784e3acd3fc9c9a24bacbbe000e25d8",
      "before": "ba158e6cf398df2f3eb1c94b788b382d1fbb8045",
      "commits": [
        {
          "sha": "a1ca3fe7d784e3acd3fc9c9a24bacbbe000e25d8",
          "author": {
            "email": "github-actions@github.com",
            "name": "GitHub Actions"
          },
          "message": "Update GitHub activity",
          "distinct": true,
          "url": "https://api.github.com/repos/Mwaldemar/Resume/commits/a1ca3fe7d784e3acd3fc9c9a24bacbbe000e25d8"
        }
      ]
    },
    "public": true,
    "created_at": "2025-02-28T20:21:37Z"
  }
]