[
  {
    "id": "47856085592",
    "type": "PushEvent",
    "actor": {
      "id": 102224869,
      "login": "Mwaldemar",
      "display_login": "Mwaldemar",
      "gravatar_id": "",
      "url": "https://api.github.com/users/Mwaldemar",
      "avatar_url": "https://avatars.githubusercontent.com/u/102224869?"
    },
    "repo": {
      "id": 925695263,
      "name": "Mwaldemar/Resume",
      "url": "https://api.github.com/repos/Mwaldemar/Resume"
    },
    "payload": {
      "repository_id": 925695263,
      "push_id": 23324787625,
      "size": 1,
      "distinct_size": 1,
      "ref": "refs/heads/main",
      "head": "47adb1815b449412045ce0fd05d3e3045e5fdf5c",
      "before": "65af9b00130e09ae7f38b1c48ab504f4d2779fdb",
      "commits": [
        {
          "sha": "47adb1815b449412045ce0fd05d3e3045e5fdf5c",
          "author": {
            "email": "github-actions@github.com",
            "name": "GitHub Actions"
          },
          "message": "Update GitHub activity",
          "distinct": true,
          "url": "https://api.github.com/repos/Mwaldemar/Resume/commits/47adb1815b449412045ce0fd05d3e3045e5fdf5c"
        }
      ]
    },
    "public": true,
    "created_at": "2025-03-22T22:17:49Z"
  },
  {
    "id": "47855495765",
    "type": "PushEvent",
    "actor": {
      "id": 102224869,
      "login": "Mwaldemar",
      "display_login": "Mwaldemar",
      "gravatar_id": "",
      "url": "https://api.github.com/users/Mwaldemar",
      "avatar_url": "https://avatars.githubusercontent.com/u/102224869?"
    },
    "repo": {
      "id": 925695263,
      "name": "Mwaldemar/Resume",
      "url": "https://api.github.com/repos/Mwaldemar/Resume"
    },
    "payload": {
      "repository_id": 925695263,
      "push_id": 23324391400,
      "size": 1,
      "distinct_size": 1,
      "ref": "refs/heads/main",
      "head": "65af9b00130e09ae7f38b1c48ab504f4d2779fdb",
      "before": "31843d83280b9534f6f6a2f2161796abc0547d40",
      "commits": [
        {
          "sha": "65af9b00130e09ae7f38b1c48ab504f4d2779fdb",
          "author": {
            "email": "github-actions@github.com",
            "name": "GitHub Actions"
          },
          "message": "Update GitHub activity",
          "distinct": true,
          "url": "https://api.github.com/repos/Mwaldemar/Resume/commits/65af9b00130e09ae7f38b1c48ab504f4d2779fdb"
        }
      ]
    },
    "public": true,
    "created_at": "2025-03-22T21:17:51Z"
  },
  {
    "id": "47854890055",
    "type": "PushEvent",
    "actor": {
      "id": 102224869,
      "login": "Mwaldemar",
      "display_login": "Mwaldemar",
      "gravatar_id": "",
      "url": "https://api.github.com/users/Mwaldemar",
      "avatar_url": "https://avatars.githubusercontent.com/u/102224869?"
    },
    "repo": {
      "id": 925695263,
      "name": "Mwaldemar/Resume",
      "url": "https://api.github.com/repos/Mwaldemar/Resume"
    },
    "payload": {
      "repository_id": 925695263,
      "push_id": 23323994290,
      "size": 1,
      "distinct_size": 1,
      "ref": "refs/heads/main",
      "head": "31843d83280b9534f6f6a2f2161796abc0547d40",
      "before": "48bc25e7cb6dae3b6e03ec531ec59818c56dd0f5",
      "commits": [
        {
          "sha": "31843d83280b9534f6f6a2f2161796abc0547d40",
          "author": {
            "email": "github-actions@github.com",
            "name": "GitHub Actions"
          },
          "message": "Update GitHub activity",
          "distinct": true,
          "url": "https://api.github.com/repos/Mwaldemar/Resume/commits/31843d83280b9534f6f6a2f2161796abc0547d40"
        }
      ]
    },
    "public": true,
    "created_at": "2025-03-22T20:20:26Z"
  },
  {
    "id": "47854205722",
    "type": "PushEvent",
    "actor": {
      "id": 102224869,
      "login": "Mwaldemar",
      "display_login": "Mwaldemar",
      "gravatar_id": "",
      "url": "https://api.github.com/users/Mwaldemar",
      "avatar_url": "https://avatars.githubusercontent.com/u/102224869?"
    },
    "repo": {
      "id": 925695263,
      "name": "Mwaldemar/Resume",
      "url": "https://api.github.com/repos/Mwaldemar/Resume"
    },
    "payload": {
      "repository_id": 925695263,
      "push_id": 23323540312,
      "size": 1,
      "distinct_size": 1,
      "ref": "refs/heads/main",
      "head": "48bc25e7cb6dae3b6e03ec531ec59818c56dd0f5",
      "before": "576f98e8756b7749a5cf4f5839f67b63c7361f20",
      "commits": [
        {
          "sha": "48bc25e7cb6dae3b6e03ec531ec59818c56dd0f5",
          "author": {
            "email": "github-actions@github.com",
            "name": "GitHub Actions"
          },
          "message": "Update GitHub activity",
          "distinct": true,
          "url": "https://api.github.com/repos/Mwaldemar/Resume/commits/48bc25e7cb6dae3b6e03ec531ec59818c56dd0f5"
        }
      ]
    },
    "public": true,
    "created_at": "2025-03-22T19:16:30Z"
  },
  {
    "id": "47853650568",
    "type": "PushEvent",
    "actor": {
      "id": 102224869,
      "login": "Mwaldemar",
      "display_login": "Mwaldemar",
      "gravatar_id": "",
      "url": "https://api.github.com/users/Mwaldemar",
      "avatar_url": "https://avatars.githubusercontent.com/u/102224869?"
    },
    "repo": {
      "id": 925695263,
      "name": "Mwaldemar/Resume",
      "url": "https://api.github.com/repos/Mwaldemar/Resume"
    },
    "payload": {
      "repository_id": 925695263,
      "push_id": 23323147551,
      "size": 1,
      "distinct_size": 1,
      "ref": "refs/heads/main",
      "head": "576f98e8756b7749a5cf4f5839f67b63c7361f20",
      "before": "8cdf028cf1a52365f69bbaf944a995dbd05c6851",
      "commits": [
        {
          "sha": "576f98e8756b7749a5cf4f5839f67b63c7361f20",
          "author": {
            "email": "github-actions@github.com",
            "name": "GitHub Actions"
          },
          "message": "Update GitHub activity",
          "distinct": true,
          "url": "https://api.github.com/repos/Mwaldemar/Resume/commits/576f98e8756b7749a5cf4f5839f67b63c7361f20"
        }
      ]
    },
    "public": true,
    "created_at": "2025-03-22T18:26:03Z"
  },
  {
    "id": "47852846659",
    "type": "PushEvent",
    "actor": {
      "id": 102224869,
      "login": "Mwaldemar",
      "display_login": "Mwaldemar",
      "gravatar_id": "",
      "url": "https://api.github.com/users/Mwaldemar",
      "avatar_url": "https://avatars.githubusercontent.com/u/102224869?"
    },
    "repo": {
      "id": 925695263,
      "name": "Mwaldemar/Resume",
      "url": "https://api.github.com/repos/Mwaldemar/Resume"
    },
    "payload": {
      "repository_id": 925695263,
      "push_id": 23322576612,
      "size": 1,
      "distinct_size": 1,
      "ref": "refs/heads/main",
      "head": "8cdf028cf1a52365f69bbaf944a995dbd05c6851",
      "before": "5df6bf9083a3d4180b22e6971e1a77bb454d74d0",
      "commits": [
        {
          "sha": "8cdf028cf1a52365f69bbaf944a995dbd05c6851",
          "author": {
            "email": "github-actions@github.com",
            "name": "GitHub Actions"
          },
          "message": "Update GitHub activity",
          "distinct": true,
          "url": "https://api.github.com/repos/Mwaldemar/Resume/commits/8cdf028cf1a52365f69bbaf944a995dbd05c6851"
        }
      ]
    },
    "public": true,
    "created_at": "2025-03-22T17:15:56Z"
  },
  {
    "id": "47852252366",
    "type": "PushEvent",
    "actor": {
      "id": 102224869,
      "login": "Mwaldemar",
      "display_login": "Mwaldemar",
      "gravatar_id": "",
      "url": "https://api.github.com/users/Mwaldemar",
      "avatar_url": "https://avatars.githubusercontent.com/u/102224869?"
    },
    "repo": {
      "id": 925695263,
      "name": "Mwaldemar/Resume",
      "url": "https://api.github.com/repos/Mwaldemar/Resume"
    },
    "payload": {
      "repository_id": 925695263,
      "push_id": 23322171086,
      "size": 1,
      "distinct_size": 1,
      "ref": "refs/heads/main",
      "head": "5df6bf9083a3d4180b22e6971e1a77bb454d74d0",
      "before": "63cea2e52ca6f1d283057a2cb95e43ef289f7e16",
      "commits": [
        {
          "sha": "5df6bf9083a3d4180b22e6971e1a77bb454d74d0",
          "author": {
            "email": "github-actions@github.com",
            "name": "GitHub Actions"
          },
          "message": "Update GitHub activity",
          "distinct": true,
          "url": "https://api.github.com/repos/Mwaldemar/Resume/commits/5df6bf9083a3d4180b22e6971e1a77bb454d74d0"
        }
      ]
    },
    "public": true,
    "created_at": "2025-03-22T16:23:05Z"
  },
  {
    "id": "47852114732",
    "type": "PushEvent",
    "actor": {
      "id": 102224869,
      "login": "Mwaldemar",
      "display_login": "Mwaldemar",
      "gravatar_id": "",
      "url": "https://api.github.com/users/Mwaldemar",
      "avatar_url": "https://avatars.githubusercontent.com/u/102224869?"
    },
    "repo": {
      "id": 925695263,
      "name": "Mwaldemar/Resume",
      "url": "https://api.github.com/repos/Mwaldemar/Resume"
    },
    "payload": {
      "repository_id": 925695263,
      "push_id": 23322075268,
      "size": 1,
      "distinct_size": 1,
      "ref": "refs/heads/main",
      "head": "63cea2e52ca6f1d283057a2cb95e43ef289f7e16",
      "before": "2153332d994fd5a0e1f4b65e39ab4adcba23f975",
      "commits": [
        {
          "sha": "63cea2e52ca6f1d283057a2cb95e43ef289f7e16",
          "author": {
            "email": "github-actions@github.com",
            "name": "GitHub Actions"
          },
          "message": "Update GitHub repositories",
          "distinct": true,
          "url": "https://api.github.com/repos/Mwaldemar/Resume/commits/63cea2e52ca6f1d283057a2cb95e43ef289f7e16"
        }
      ]
    },
    "public": true,
    "created_at": "2025-03-22T16:10:52Z"
  },
  {
    "id": "47851526939",
    "type": "PushEvent",
    "actor": {
      "id": 102224869,
      "login": "Mwaldemar",
      "display_login": "Mwaldemar",
      "gravatar_id": "",
      "url": "https://api.github.com/users/Mwaldemar",
      "avatar_url": "https://avatars.githubusercontent.com/u/102224869?"
    },
    "repo": {
      "id": 925695263,
      "name": "Mwaldemar/Resume",
      "url": "https://api.github.com/repos/Mwaldemar/Resume"
    },
    "payload": {
      "repository_id": 925695263,
      "push_id": 23321673570,
      "size": 1,
      "distinct_size": 1,
      "ref": "refs/heads/main",
      "head": "2153332d994fd5a0e1f4b65e39ab4adcba23f975",
      "before": "2d7ea8ae9831e9124db5d8fecd6499f14866c96f",
      "commits": [
        {
          "sha": "2153332d994fd5a0e1f4b65e39ab4adcba23f975",
          "author": {
            "email": "github-actions@github.com",
            "name": "GitHub Actions"
          },
          "message": "Update GitHub activity",
          "distinct": true,
          "url": "https://api.github.com/repos/Mwaldemar/Resume/commits/2153332d994fd5a0e1f4b65e39ab4adcba23f975"
        }
      ]
    },
    "public": true,
    "created_at": "2025-03-22T15:18:41Z"
  },
  {
    "id": "47850804215",
    "type": "PushEvent",
    "actor": {
      "id": 102224869,
      "login": "Mwaldemar",
      "display_login": "Mwaldemar",
      "gravatar_id": "",
      "url": "https://api.github.com/users/Mwaldemar",
      "avatar_url": "https://avatars.githubusercontent.com/u/102224869?"
    },
    "repo": {
      "id": 925695263,
      "name": "Mwaldemar/Resume",
      "url": "https://api.github.com/repos/Mwaldemar/Resume"
    },
    "payload": {
      "repository_id": 925695263,
      "push_id": 23321180778,
      "size": 1,
      "distinct_size": 1,
      "ref": "refs/heads/main",
      "head": "2d7ea8ae9831e9124db5d8fecd6499f14866c96f",
      "before": "d9e6b4bf5bf91a84480ad6b18e80416fe9f7979b",
      "commits": [
        {
          "sha": "2d7ea8ae9831e9124db5d8fecd6499f14866c96f",
          "author": {
            "email": "github-actions@github.com",
            "name": "GitHub Actions"
          },
          "message": "Update GitHub activity",
          "distinct": true,
          "url": "https://api.github.com/repos/Mwaldemar/Resume/commits/2d7ea8ae9831e9124db5d8fecd6499f14866c96f"
        }
      ]
    },
    "public": true,
    "created_at": "2025-03-22T14:18:05Z"
  }
]