[
  {
    "id": "46778261244",
    "type": "PushEvent",
    "actor": {
      "id": 102224869,
      "login": "Mwaldemar",
      "display_login": "Mwaldemar",
      "gravatar_id": "",
      "url": "https://api.github.com/users/Mwaldemar",
      "avatar_url": "https://avatars.githubusercontent.com/u/102224869?"
    },
    "repo": {
      "id": 925695263,
      "name": "Mwaldemar/Resume",
      "url": "https://api.github.com/repos/Mwaldemar/Resume"
    },
    "payload": {
      "repository_id": 925695263,
      "push_id": 22764733943,
      "size": 1,
      "distinct_size": 1,
      "ref": "refs/heads/main",
      "head": "872ed304119e579176d4e2c41de447ad22d01999",
      "before": "d91c4e92ae76a6859560700851ce4c848a22475b",
      "commits": [
        {
          "sha": "872ed304119e579176d4e2c41de447ad22d01999",
          "author": {
            "email": "github-actions@github.com",
            "name": "GitHub Actions"
          },
          "message": "Update GitHub repositories",
          "distinct": true,
          "url": "https://api.github.com/repos/Mwaldemar/Resume/commits/872ed304119e579176d4e2c41de447ad22d01999"
        }
      ]
    },
    "public": true,
    "created_at": "2025-02-20T13:44:00Z"
  },
  {
    "id": "46777421274",
    "type": "PushEvent",
    "actor": {
      "id": 102224869,
      "login": "Mwaldemar",
      "display_login": "Mwaldemar",
      "gravatar_id": "",
      "url": "https://api.github.com/users/Mwaldemar",
      "avatar_url": "https://avatars.githubusercontent.com/u/102224869?"
    },
    "repo": {
      "id": 925695263,
      "name": "Mwaldemar/Resume",
      "url": "https://api.github.com/repos/Mwaldemar/Resume"
    },
    "payload": {
      "repository_id": 925695263,
      "push_id": 22764322447,
      "size": 2,
      "distinct_size": 1,
      "ref": "refs/heads/main",
      "head": "d91c4e92ae76a6859560700851ce4c848a22475b",
      "before": "e2a415529d573bdf49ef29c49498d8d240123734",
      "commits": [
        {
          "sha": "742ede3016aabba081c2d7f2452408fb438c2587",
          "author": {
            "email": "304837@via.dk",
            "name": "Mwaldemar"
          },
          "message": "another small fix to timezone",
          "distinct": false,
          "url": "https://api.github.com/repos/Mwaldemar/Resume/commits/742ede3016aabba081c2d7f2452408fb438c2587"
        },
        {
          "sha": "d91c4e92ae76a6859560700851ce4c848a22475b",
          "author": {
            "email": "102224869+Mwaldemar@users.noreply.github.com",
            "name": "Mikkel W. Johannessen"
          },
          "message": "Merge pull request #36 from Mwaldemar/timezoneFix2\n\nanother small fix to timezone",
          "distinct": true,
          "url": "https://api.github.com/repos/Mwaldemar/Resume/commits/d91c4e92ae76a6859560700851ce4c848a22475b"
        }
      ]
    },
    "public": true,
    "created_at": "2025-02-20T13:23:26Z"
  },
  {
    "id": "46777420580",
    "type": "PullRequestEvent",
    "actor": {
      "id": 102224869,
      "login": "Mwaldemar",
      "display_login": "Mwaldemar",
      "gravatar_id": "",
      "url": "https://api.github.com/users/Mwaldemar",
      "avatar_url": "https://avatars.githubusercontent.com/u/102224869?"
    },
    "repo": {
      "id": 925695263,
      "name": "Mwaldemar/Resume",
      "url": "https://api.github.com/repos/Mwaldemar/Resume"
    },
    "payload": {
      "action": "closed",
      "number": 36,
      "pull_request": {
        "url": "https://api.github.com/repos/Mwaldemar/Resume/pulls/36",
        "id": 2347105678,
        "node_id": "PR_kwDONyz9H86L5f2O",
        "html_url": "https://github.com/Mwaldemar/Resume/pull/36",
        "diff_url": "https://github.com/Mwaldemar/Resume/pull/36.diff",
        "patch_url": "https://github.com/Mwaldemar/Resume/pull/36.patch",
        "issue_url": "https://api.github.com/repos/Mwaldemar/Resume/issues/36",
        "number": 36,
        "state": "closed",
        "locked": false,
        "title": "another small fix to timezone",
        "user": {
          "login": "Mwaldemar",
          "id": 102224869,
          "node_id": "U_kgDOBhfT5Q",
          "avatar_url": "https://avatars.githubusercontent.com/u/102224869?v=4",
          "gravatar_id": "",
          "url": "https://api.github.com/users/Mwaldemar",
          "html_url": "https://github.com/Mwaldemar",
          "followers_url": "https://api.github.com/users/Mwaldemar/followers",
          "following_url": "https://api.github.com/users/Mwaldemar/following{/other_user}",
          "gists_url": "https://api.github.com/users/Mwaldemar/gists{/gist_id}",
          "starred_url": "https://api.github.com/users/Mwaldemar/starred{/owner}{/repo}",
          "subscriptions_url": "https://api.github.com/users/Mwaldemar/subscriptions",
          "organizations_url": "https://api.github.com/users/Mwaldemar/orgs",
          "repos_url": "https://api.github.com/users/Mwaldemar/repos",
          "events_url": "https://api.github.com/users/Mwaldemar/events{/privacy}",
          "received_events_url": "https://api.github.com/users/Mwaldemar/received_events",
          "type": "User",
          "user_view_type": "public",
          "site_admin": false
        },
        "body": null,
        "created_at": "2025-02-20T13:23:18Z",
        "updated_at": "2025-02-20T13:23:24Z",
        "closed_at": "2025-02-20T13:23:24Z",
        "merged_at": "2025-02-20T13:23:24Z",
        "merge_commit_sha": "d91c4e92ae76a6859560700851ce4c848a22475b",
        "assignee": null,
        "assignees": [],
        "requested_reviewers": [],
        "requested_teams": [],
        "labels": [],
        "milestone": null,
        "draft": false,
        "commits_url": "https://api.github.com/repos/Mwaldemar/Resume/pulls/36/commits",
        "review_comments_url": "https://api.github.com/repos/Mwaldemar/Resume/pulls/36/comments",
        "review_comment_url": "https://api.github.com/repos/Mwaldemar/Resume/pulls/comments{/number}",
        "comments_url": "https://api.github.com/repos/Mwaldemar/Resume/issues/36/comments",
        "statuses_url": "https://api.github.com/repos/Mwaldemar/Resume/statuses/742ede3016aabba081c2d7f2452408fb438c2587",
        "head": {
          "label": "Mwaldemar:timezoneFix2",
          "ref": "timezoneFix2",
          "sha": "742ede3016aabba081c2d7f2452408fb438c2587",
          "user": {
            "login": "Mwaldemar",
            "id": 102224869,
            "node_id": "U_kgDOBhfT5Q",
            "avatar_url": "https://avatars.githubusercontent.com/u/102224869?v=4",
            "gravatar_id": "",
            "url": "https://api.github.com/users/Mwaldemar",
            "html_url": "https://github.com/Mwaldemar",
            "followers_url": "https://api.github.com/users/Mwaldemar/followers",
            "following_url": "https://api.github.com/users/Mwaldemar/following{/other_user}",
            "gists_url": "https://api.github.com/users/Mwaldemar/gists{/gist_id}",
            "starred_url": "https://api.github.com/users/Mwaldemar/starred{/owner}{/repo}",
            "subscriptions_url": "https://api.github.com/users/Mwaldemar/subscriptions",
            "organizations_url": "https://api.github.com/users/Mwaldemar/orgs",
            "repos_url": "https://api.github.com/users/Mwaldemar/repos",
            "events_url": "https://api.github.com/users/Mwaldemar/events{/privacy}",
            "received_events_url": "https://api.github.com/users/Mwaldemar/received_events",
            "type": "User",
            "user_view_type": "public",
            "site_admin": false
          },
          "repo": {
            "id": 925695263,
            "node_id": "R_kgDONyz9Hw",
            "name": "Resume",
            "full_name": "Mwaldemar/Resume",
            "private": false,
            "owner": {
              "login": "Mwaldemar",
              "id": 102224869,
              "node_id": "U_kgDOBhfT5Q",
              "avatar_url": "https://avatars.githubusercontent.com/u/102224869?v=4",
              "gravatar_id": "",
              "url": "https://api.github.com/users/Mwaldemar",
              "html_url": "https://github.com/Mwaldemar",
              "followers_url": "https://api.github.com/users/Mwaldemar/followers",
              "following_url": "https://api.github.com/users/Mwaldemar/following{/other_user}",
              "gists_url": "https://api.github.com/users/Mwaldemar/gists{/gist_id}",
              "starred_url": "https://api.github.com/users/Mwaldemar/starred{/owner}{/repo}",
              "subscriptions_url": "https://api.github.com/users/Mwaldemar/subscriptions",
              "organizations_url": "https://api.github.com/users/Mwaldemar/orgs",
              "repos_url": "https://api.github.com/users/Mwaldemar/repos",
              "events_url": "https://api.github.com/users/Mwaldemar/events{/privacy}",
              "received_events_url": "https://api.github.com/users/Mwaldemar/received_events",
              "type": "User",
              "user_view_type": "public",
              "site_admin": false
            },
            "html_url": "https://github.com/Mwaldemar/Resume",
            "description": "Development of resume website",
            "fork": false,
            "url": "https://api.github.com/repos/Mwaldemar/Resume",
            "forks_url": "https://api.github.com/repos/Mwaldemar/Resume/forks",
            "keys_url": "https://api.github.com/repos/Mwaldemar/Resume/keys{/key_id}",
            "collaborators_url": "https://api.github.com/repos/Mwaldemar/Resume/collaborators{/collaborator}",
            "teams_url": "https://api.github.com/repos/Mwaldemar/Resume/teams",
            "hooks_url": "https://api.github.com/repos/Mwaldemar/Resume/hooks",
            "issue_events_url": "https://api.github.com/repos/Mwaldemar/Resume/issues/events{/number}",
            "events_url": "https://api.github.com/repos/Mwaldemar/Resume/events",
            "assignees_url": "https://api.github.com/repos/Mwaldemar/Resume/assignees{/user}",
            "branches_url": "https://api.github.com/repos/Mwaldemar/Resume/branches{/branch}",
            "tags_url": "https://api.github.com/repos/Mwaldemar/Resume/tags",
            "blobs_url": "https://api.github.com/repos/Mwaldemar/Resume/git/blobs{/sha}",
            "git_tags_url": "https://api.github.com/repos/Mwaldemar/Resume/git/tags{/sha}",
            "git_refs_url": "https://api.github.com/repos/Mwaldemar/Resume/git/refs{/sha}",
            "trees_url": "https://api.github.com/repos/Mwaldemar/Resume/git/trees{/sha}",
            "statuses_url": "https://api.github.com/repos/Mwaldemar/Resume/statuses/{sha}",
            "languages_url": "https://api.github.com/repos/Mwaldemar/Resume/languages",
            "stargazers_url": "https://api.github.com/repos/Mwaldemar/Resume/stargazers",
            "contributors_url": "https://api.github.com/repos/Mwaldemar/Resume/contributors",
            "subscribers_url": "https://api.github.com/repos/Mwaldemar/Resume/subscribers",
            "subscription_url": "https://api.github.com/repos/Mwaldemar/Resume/subscription",
            "commits_url": "https://api.github.com/repos/Mwaldemar/Resume/commits{/sha}",
            "git_commits_url": "https://api.github.com/repos/Mwaldemar/Resume/git/commits{/sha}",
            "comments_url": "https://api.github.com/repos/Mwaldemar/Resume/comments{/number}",
            "issue_comment_url": "https://api.github.com/repos/Mwaldemar/Resume/issues/comments{/number}",
            "contents_url": "https://api.github.com/repos/Mwaldemar/Resume/contents/{+path}",
            "compare_url": "https://api.github.com/repos/Mwaldemar/Resume/compare/{base}...{head}",
            "merges_url": "https://api.github.com/repos/Mwaldemar/Resume/merges",
            "archive_url": "https://api.github.com/repos/Mwaldemar/Resume/{archive_format}{/ref}",
            "downloads_url": "https://api.github.com/repos/Mwaldemar/Resume/downloads",
            "issues_url": "https://api.github.com/repos/Mwaldemar/Resume/issues{/number}",
            "pulls_url": "https://api.github.com/repos/Mwaldemar/Resume/pulls{/number}",
            "milestones_url": "https://api.github.com/repos/Mwaldemar/Resume/milestones{/number}",
            "notifications_url": "https://api.github.com/repos/Mwaldemar/Resume/notifications{?since,all,participating}",
            "labels_url": "https://api.github.com/repos/Mwaldemar/Resume/labels{/name}",
            "releases_url": "https://api.github.com/repos/Mwaldemar/Resume/releases{/id}",
            "deployments_url": "https://api.github.com/repos/Mwaldemar/Resume/deployments",
            "created_at": "2025-02-01T14:15:49Z",
            "updated_at": "2025-02-20T13:12:29Z",
            "pushed_at": "2025-02-20T13:22:35Z",
            "git_url": "git://github.com/Mwaldemar/Resume.git",
            "ssh_url": "git@github.com:Mwaldemar/Resume.git",
            "clone_url": "https://github.com/Mwaldemar/Resume.git",
            "svn_url": "https://github.com/Mwaldemar/Resume",
            "homepage": "https://resume-ruby-ten-65.vercel.app",
            "size": 1446,
            "stargazers_count": 0,
            "watchers_count": 0,
            "language": "TypeScript",
            "has_issues": true,
            "has_projects": true,
            "has_downloads": true,
            "has_wiki": true,
            "has_pages": false,
            "has_discussions": false,
            "forks_count": 0,
            "mirror_url": null,
            "archived": false,
            "disabled": false,
            "open_issues_count": 0,
            "license": null,
            "allow_forking": true,
            "is_template": false,
            "web_commit_signoff_required": false,
            "topics": [],
            "visibility": "public",
            "forks": 0,
            "open_issues": 0,
            "watchers": 0,
            "default_branch": "main"
          }
        },
        "base": {
          "label": "Mwaldemar:main",
          "ref": "main",
          "sha": "e2a415529d573bdf49ef29c49498d8d240123734",
          "user": {
            "login": "Mwaldemar",
            "id": 102224869,
            "node_id": "U_kgDOBhfT5Q",
            "avatar_url": "https://avatars.githubusercontent.com/u/102224869?v=4",
            "gravatar_id": "",
            "url": "https://api.github.com/users/Mwaldemar",
            "html_url": "https://github.com/Mwaldemar",
            "followers_url": "https://api.github.com/users/Mwaldemar/followers",
            "following_url": "https://api.github.com/users/Mwaldemar/following{/other_user}",
            "gists_url": "https://api.github.com/users/Mwaldemar/gists{/gist_id}",
            "starred_url": "https://api.github.com/users/Mwaldemar/starred{/owner}{/repo}",
            "subscriptions_url": "https://api.github.com/users/Mwaldemar/subscriptions",
            "organizations_url": "https://api.github.com/users/Mwaldemar/orgs",
            "repos_url": "https://api.github.com/users/Mwaldemar/repos",
            "events_url": "https://api.github.com/users/Mwaldemar/events{/privacy}",
            "received_events_url": "https://api.github.com/users/Mwaldemar/received_events",
            "type": "User",
            "user_view_type": "public",
            "site_admin": false
          },
          "repo": {
            "id": 925695263,
            "node_id": "R_kgDONyz9Hw",
            "name": "Resume",
            "full_name": "Mwaldemar/Resume",
            "private": false,
            "owner": {
              "login": "Mwaldemar",
              "id": 102224869,
              "node_id": "U_kgDOBhfT5Q",
              "avatar_url": "https://avatars.githubusercontent.com/u/102224869?v=4",
              "gravatar_id": "",
              "url": "https://api.github.com/users/Mwaldemar",
              "html_url": "https://github.com/Mwaldemar",
              "followers_url": "https://api.github.com/users/Mwaldemar/followers",
              "following_url": "https://api.github.com/users/Mwaldemar/following{/other_user}",
              "gists_url": "https://api.github.com/users/Mwaldemar/gists{/gist_id}",
              "starred_url": "https://api.github.com/users/Mwaldemar/starred{/owner}{/repo}",
              "subscriptions_url": "https://api.github.com/users/Mwaldemar/subscriptions",
              "organizations_url": "https://api.github.com/users/Mwaldemar/orgs",
              "repos_url": "https://api.github.com/users/Mwaldemar/repos",
              "events_url": "https://api.github.com/users/Mwaldemar/events{/privacy}",
              "received_events_url": "https://api.github.com/users/Mwaldemar/received_events",
              "type": "User",
              "user_view_type": "public",
              "site_admin": false
            },
            "html_url": "https://github.com/Mwaldemar/Resume",
            "description": "Development of resume website",
            "fork": false,
            "url": "https://api.github.com/repos/Mwaldemar/Resume",
            "forks_url": "https://api.github.com/repos/Mwaldemar/Resume/forks",
            "keys_url": "https://api.github.com/repos/Mwaldemar/Resume/keys{/key_id}",
            "collaborators_url": "https://api.github.com/repos/Mwaldemar/Resume/collaborators{/collaborator}",
            "teams_url": "https://api.github.com/repos/Mwaldemar/Resume/teams",
            "hooks_url": "https://api.github.com/repos/Mwaldemar/Resume/hooks",
            "issue_events_url": "https://api.github.com/repos/Mwaldemar/Resume/issues/events{/number}",
            "events_url": "https://api.github.com/repos/Mwaldemar/Resume/events",
            "assignees_url": "https://api.github.com/repos/Mwaldemar/Resume/assignees{/user}",
            "branches_url": "https://api.github.com/repos/Mwaldemar/Resume/branches{/branch}",
            "tags_url": "https://api.github.com/repos/Mwaldemar/Resume/tags",
            "blobs_url": "https://api.github.com/repos/Mwaldemar/Resume/git/blobs{/sha}",
            "git_tags_url": "https://api.github.com/repos/Mwaldemar/Resume/git/tags{/sha}",
            "git_refs_url": "https://api.github.com/repos/Mwaldemar/Resume/git/refs{/sha}",
            "trees_url": "https://api.github.com/repos/Mwaldemar/Resume/git/trees{/sha}",
            "statuses_url": "https://api.github.com/repos/Mwaldemar/Resume/statuses/{sha}",
            "languages_url": "https://api.github.com/repos/Mwaldemar/Resume/languages",
            "stargazers_url": "https://api.github.com/repos/Mwaldemar/Resume/stargazers",
            "contributors_url": "https://api.github.com/repos/Mwaldemar/Resume/contributors",
            "subscribers_url": "https://api.github.com/repos/Mwaldemar/Resume/subscribers",
            "subscription_url": "https://api.github.com/repos/Mwaldemar/Resume/subscription",
            "commits_url": "https://api.github.com/repos/Mwaldemar/Resume/commits{/sha}",
            "git_commits_url": "https://api.github.com/repos/Mwaldemar/Resume/git/commits{/sha}",
            "comments_url": "https://api.github.com/repos/Mwaldemar/Resume/comments{/number}",
            "issue_comment_url": "https://api.github.com/repos/Mwaldemar/Resume/issues/comments{/number}",
            "contents_url": "https://api.github.com/repos/Mwaldemar/Resume/contents/{+path}",
            "compare_url": "https://api.github.com/repos/Mwaldemar/Resume/compare/{base}...{head}",
            "merges_url": "https://api.github.com/repos/Mwaldemar/Resume/merges",
            "archive_url": "https://api.github.com/repos/Mwaldemar/Resume/{archive_format}{/ref}",
            "downloads_url": "https://api.github.com/repos/Mwaldemar/Resume/downloads",
            "issues_url": "https://api.github.com/repos/Mwaldemar/Resume/issues{/number}",
            "pulls_url": "https://api.github.com/repos/Mwaldemar/Resume/pulls{/number}",
            "milestones_url": "https://api.github.com/repos/Mwaldemar/Resume/milestones{/number}",
            "notifications_url": "https://api.github.com/repos/Mwaldemar/Resume/notifications{?since,all,participating}",
            "labels_url": "https://api.github.com/repos/Mwaldemar/Resume/labels{/name}",
            "releases_url": "https://api.github.com/repos/Mwaldemar/Resume/releases{/id}",
            "deployments_url": "https://api.github.com/repos/Mwaldemar/Resume/deployments",
            "created_at": "2025-02-01T14:15:49Z",
            "updated_at": "2025-02-20T13:12:29Z",
            "pushed_at": "2025-02-20T13:22:35Z",
            "git_url": "git://github.com/Mwaldemar/Resume.git",
            "ssh_url": "git@github.com:Mwaldemar/Resume.git",
            "clone_url": "https://github.com/Mwaldemar/Resume.git",
            "svn_url": "https://github.com/Mwaldemar/Resume",
            "homepage": "https://resume-ruby-ten-65.vercel.app",
            "size": 1446,
            "stargazers_count": 0,
            "watchers_count": 0,
            "language": "TypeScript",
            "has_issues": true,
            "has_projects": true,
            "has_downloads": true,
            "has_wiki": true,
            "has_pages": false,
            "has_discussions": false,
            "forks_count": 0,
            "mirror_url": null,
            "archived": false,
            "disabled": false,
            "open_issues_count": 0,
            "license": null,
            "allow_forking": true,
            "is_template": false,
            "web_commit_signoff_required": false,
            "topics": [],
            "visibility": "public",
            "forks": 0,
            "open_issues": 0,
            "watchers": 0,
            "default_branch": "main"
          }
        },
        "_links": {
          "self": {
            "href": "https://api.github.com/repos/Mwaldemar/Resume/pulls/36"
          },
          "html": {
            "href": "https://github.com/Mwaldemar/Resume/pull/36"
          },
          "issue": {
            "href": "https://api.github.com/repos/Mwaldemar/Resume/issues/36"
          },
          "comments": {
            "href": "https://api.github.com/repos/Mwaldemar/Resume/issues/36/comments"
          },
          "review_comments": {
            "href": "https://api.github.com/repos/Mwaldemar/Resume/pulls/36/comments"
          },
          "review_comment": {
            "href": "https://api.github.com/repos/Mwaldemar/Resume/pulls/comments{/number}"
          },
          "commits": {
            "href": "https://api.github.com/repos/Mwaldemar/Resume/pulls/36/commits"
          },
          "statuses": {
            "href": "https://api.github.com/repos/Mwaldemar/Resume/statuses/742ede3016aabba081c2d7f2452408fb438c2587"
          }
        },
        "author_association": "OWNER",
        "auto_merge": null,
        "active_lock_reason": null,
        "merged": true,
        "mergeable": null,
        "rebaseable": null,
        "mergeable_state": "unknown",
        "merged_by": {
          "login": "Mwaldemar",
          "id": 102224869,
          "node_id": "U_kgDOBhfT5Q",
          "avatar_url": "https://avatars.githubusercontent.com/u/102224869?v=4",
          "gravatar_id": "",
          "url": "https://api.github.com/users/Mwaldemar",
          "html_url": "https://github.com/Mwaldemar",
          "followers_url": "https://api.github.com/users/Mwaldemar/followers",
          "following_url": "https://api.github.com/users/Mwaldemar/following{/other_user}",
          "gists_url": "https://api.github.com/users/Mwaldemar/gists{/gist_id}",
          "starred_url": "https://api.github.com/users/Mwaldemar/starred{/owner}{/repo}",
          "subscriptions_url": "https://api.github.com/users/Mwaldemar/subscriptions",
          "organizations_url": "https://api.github.com/users/Mwaldemar/orgs",
          "repos_url": "https://api.github.com/users/Mwaldemar/repos",
          "events_url": "https://api.github.com/users/Mwaldemar/events{/privacy}",
          "received_events_url": "https://api.github.com/users/Mwaldemar/received_events",
          "type": "User",
          "user_view_type": "public",
          "site_admin": false
        },
        "comments": 1,
        "review_comments": 0,
        "maintainer_can_modify": false,
        "commits": 1,
        "additions": 3,
        "deletions": 2,
        "changed_files": 1
      }
    },
    "public": true,
    "created_at": "2025-02-20T13:23:25Z"
  },
  {
    "id": "46777416756",
    "type": "PullRequestEvent",
    "actor": {
      "id": 102224869,
      "login": "Mwaldemar",
      "display_login": "Mwaldemar",
      "gravatar_id": "",
      "url": "https://api.github.com/users/Mwaldemar",
      "avatar_url": "https://avatars.githubusercontent.com/u/102224869?"
    },
    "repo": {
      "id": 925695263,
      "name": "Mwaldemar/Resume",
      "url": "https://api.github.com/repos/Mwaldemar/Resume"
    },
    "payload": {
      "action": "opened",
      "number": 36,
      "pull_request": {
        "url": "https://api.github.com/repos/Mwaldemar/Resume/pulls/36",
        "id": 2347105678,
        "node_id": "PR_kwDONyz9H86L5f2O",
        "html_url": "https://github.com/Mwaldemar/Resume/pull/36",
        "diff_url": "https://github.com/Mwaldemar/Resume/pull/36.diff",
        "patch_url": "https://github.com/Mwaldemar/Resume/pull/36.patch",
        "issue_url": "https://api.github.com/repos/Mwaldemar/Resume/issues/36",
        "number": 36,
        "state": "open",
        "locked": false,
        "title": "another small fix to timezone",
        "user": {
          "login": "Mwaldemar",
          "id": 102224869,
          "node_id": "U_kgDOBhfT5Q",
          "avatar_url": "https://avatars.githubusercontent.com/u/102224869?v=4",
          "gravatar_id": "",
          "url": "https://api.github.com/users/Mwaldemar",
          "html_url": "https://github.com/Mwaldemar",
          "followers_url": "https://api.github.com/users/Mwaldemar/followers",
          "following_url": "https://api.github.com/users/Mwaldemar/following{/other_user}",
          "gists_url": "https://api.github.com/users/Mwaldemar/gists{/gist_id}",
          "starred_url": "https://api.github.com/users/Mwaldemar/starred{/owner}{/repo}",
          "subscriptions_url": "https://api.github.com/users/Mwaldemar/subscriptions",
          "organizations_url": "https://api.github.com/users/Mwaldemar/orgs",
          "repos_url": "https://api.github.com/users/Mwaldemar/repos",
          "events_url": "https://api.github.com/users/Mwaldemar/events{/privacy}",
          "received_events_url": "https://api.github.com/users/Mwaldemar/received_events",
          "type": "User",
          "user_view_type": "public",
          "site_admin": false
        },
        "body": null,
        "created_at": "2025-02-20T13:23:18Z",
        "updated_at": "2025-02-20T13:23:18Z",
        "closed_at": null,
        "merged_at": null,
        "merge_commit_sha": null,
        "assignee": null,
        "assignees": [],
        "requested_reviewers": [],
        "requested_teams": [],
        "labels": [],
        "milestone": null,
        "draft": false,
        "commits_url": "https://api.github.com/repos/Mwaldemar/Resume/pulls/36/commits",
        "review_comments_url": "https://api.github.com/repos/Mwaldemar/Resume/pulls/36/comments",
        "review_comment_url": "https://api.github.com/repos/Mwaldemar/Resume/pulls/comments{/number}",
        "comments_url": "https://api.github.com/repos/Mwaldemar/Resume/issues/36/comments",
        "statuses_url": "https://api.github.com/repos/Mwaldemar/Resume/statuses/742ede3016aabba081c2d7f2452408fb438c2587",
        "head": {
          "label": "Mwaldemar:timezoneFix2",
          "ref": "timezoneFix2",
          "sha": "742ede3016aabba081c2d7f2452408fb438c2587",
          "user": {
            "login": "Mwaldemar",
            "id": 102224869,
            "node_id": "U_kgDOBhfT5Q",
            "avatar_url": "https://avatars.githubusercontent.com/u/102224869?v=4",
            "gravatar_id": "",
            "url": "https://api.github.com/users/Mwaldemar",
            "html_url": "https://github.com/Mwaldemar",
            "followers_url": "https://api.github.com/users/Mwaldemar/followers",
            "following_url": "https://api.github.com/users/Mwaldemar/following{/other_user}",
            "gists_url": "https://api.github.com/users/Mwaldemar/gists{/gist_id}",
            "starred_url": "https://api.github.com/users/Mwaldemar/starred{/owner}{/repo}",
            "subscriptions_url": "https://api.github.com/users/Mwaldemar/subscriptions",
            "organizations_url": "https://api.github.com/users/Mwaldemar/orgs",
            "repos_url": "https://api.github.com/users/Mwaldemar/repos",
            "events_url": "https://api.github.com/users/Mwaldemar/events{/privacy}",
            "received_events_url": "https://api.github.com/users/Mwaldemar/received_events",
            "type": "User",
            "user_view_type": "public",
            "site_admin": false
          },
          "repo": {
            "id": 925695263,
            "node_id": "R_kgDONyz9Hw",
            "name": "Resume",
            "full_name": "Mwaldemar/Resume",
            "private": false,
            "owner": {
              "login": "Mwaldemar",
              "id": 102224869,
              "node_id": "U_kgDOBhfT5Q",
              "avatar_url": "https://avatars.githubusercontent.com/u/102224869?v=4",
              "gravatar_id": "",
              "url": "https://api.github.com/users/Mwaldemar",
              "html_url": "https://github.com/Mwaldemar",
              "followers_url": "https://api.github.com/users/Mwaldemar/followers",
              "following_url": "https://api.github.com/users/Mwaldemar/following{/other_user}",
              "gists_url": "https://api.github.com/users/Mwaldemar/gists{/gist_id}",
              "starred_url": "https://api.github.com/users/Mwaldemar/starred{/owner}{/repo}",
              "subscriptions_url": "https://api.github.com/users/Mwaldemar/subscriptions",
              "organizations_url": "https://api.github.com/users/Mwaldemar/orgs",
              "repos_url": "https://api.github.com/users/Mwaldemar/repos",
              "events_url": "https://api.github.com/users/Mwaldemar/events{/privacy}",
              "received_events_url": "https://api.github.com/users/Mwaldemar/received_events",
              "type": "User",
              "user_view_type": "public",
              "site_admin": false
            },
            "html_url": "https://github.com/Mwaldemar/Resume",
            "description": "Development of resume website",
            "fork": false,
            "url": "https://api.github.com/repos/Mwaldemar/Resume",
            "forks_url": "https://api.github.com/repos/Mwaldemar/Resume/forks",
            "keys_url": "https://api.github.com/repos/Mwaldemar/Resume/keys{/key_id}",
            "collaborators_url": "https://api.github.com/repos/Mwaldemar/Resume/collaborators{/collaborator}",
            "teams_url": "https://api.github.com/repos/Mwaldemar/Resume/teams",
            "hooks_url": "https://api.github.com/repos/Mwaldemar/Resume/hooks",
            "issue_events_url": "https://api.github.com/repos/Mwaldemar/Resume/issues/events{/number}",
            "events_url": "https://api.github.com/repos/Mwaldemar/Resume/events",
            "assignees_url": "https://api.github.com/repos/Mwaldemar/Resume/assignees{/user}",
            "branches_url": "https://api.github.com/repos/Mwaldemar/Resume/branches{/branch}",
            "tags_url": "https://api.github.com/repos/Mwaldemar/Resume/tags",
            "blobs_url": "https://api.github.com/repos/Mwaldemar/Resume/git/blobs{/sha}",
            "git_tags_url": "https://api.github.com/repos/Mwaldemar/Resume/git/tags{/sha}",
            "git_refs_url": "https://api.github.com/repos/Mwaldemar/Resume/git/refs{/sha}",
            "trees_url": "https://api.github.com/repos/Mwaldemar/Resume/git/trees{/sha}",
            "statuses_url": "https://api.github.com/repos/Mwaldemar/Resume/statuses/{sha}",
            "languages_url": "https://api.github.com/repos/Mwaldemar/Resume/languages",
            "stargazers_url": "https://api.github.com/repos/Mwaldemar/Resume/stargazers",
            "contributors_url": "https://api.github.com/repos/Mwaldemar/Resume/contributors",
            "subscribers_url": "https://api.github.com/repos/Mwaldemar/Resume/subscribers",
            "subscription_url": "https://api.github.com/repos/Mwaldemar/Resume/subscription",
            "commits_url": "https://api.github.com/repos/Mwaldemar/Resume/commits{/sha}",
            "git_commits_url": "https://api.github.com/repos/Mwaldemar/Resume/git/commits{/sha}",
            "comments_url": "https://api.github.com/repos/Mwaldemar/Resume/comments{/number}",
            "issue_comment_url": "https://api.github.com/repos/Mwaldemar/Resume/issues/comments{/number}",
            "contents_url": "https://api.github.com/repos/Mwaldemar/Resume/contents/{+path}",
            "compare_url": "https://api.github.com/repos/Mwaldemar/Resume/compare/{base}...{head}",
            "merges_url": "https://api.github.com/repos/Mwaldemar/Resume/merges",
            "archive_url": "https://api.github.com/repos/Mwaldemar/Resume/{archive_format}{/ref}",
            "downloads_url": "https://api.github.com/repos/Mwaldemar/Resume/downloads",
            "issues_url": "https://api.github.com/repos/Mwaldemar/Resume/issues{/number}",
            "pulls_url": "https://api.github.com/repos/Mwaldemar/Resume/pulls{/number}",
            "milestones_url": "https://api.github.com/repos/Mwaldemar/Resume/milestones{/number}",
            "notifications_url": "https://api.github.com/repos/Mwaldemar/Resume/notifications{?since,all,participating}",
            "labels_url": "https://api.github.com/repos/Mwaldemar/Resume/labels{/name}",
            "releases_url": "https://api.github.com/repos/Mwaldemar/Resume/releases{/id}",
            "deployments_url": "https://api.github.com/repos/Mwaldemar/Resume/deployments",
            "created_at": "2025-02-01T14:15:49Z",
            "updated_at": "2025-02-20T13:12:29Z",
            "pushed_at": "2025-02-20T13:22:35Z",
            "git_url": "git://github.com/Mwaldemar/Resume.git",
            "ssh_url": "git@github.com:Mwaldemar/Resume.git",
            "clone_url": "https://github.com/Mwaldemar/Resume.git",
            "svn_url": "https://github.com/Mwaldemar/Resume",
            "homepage": "https://resume-ruby-ten-65.vercel.app",
            "size": 1446,
            "stargazers_count": 0,
            "watchers_count": 0,
            "language": "TypeScript",
            "has_issues": true,
            "has_projects": true,
            "has_downloads": true,
            "has_wiki": true,
            "has_pages": false,
            "has_discussions": false,
            "forks_count": 0,
            "mirror_url": null,
            "archived": false,
            "disabled": false,
            "open_issues_count": 1,
            "license": null,
            "allow_forking": true,
            "is_template": false,
            "web_commit_signoff_required": false,
            "topics": [],
            "visibility": "public",
            "forks": 0,
            "open_issues": 1,
            "watchers": 0,
            "default_branch": "main"
          }
        },
        "base": {
          "label": "Mwaldemar:main",
          "ref": "main",
          "sha": "e2a415529d573bdf49ef29c49498d8d240123734",
          "user": {
            "login": "Mwaldemar",
            "id": 102224869,
            "node_id": "U_kgDOBhfT5Q",
            "avatar_url": "https://avatars.githubusercontent.com/u/102224869?v=4",
            "gravatar_id": "",
            "url": "https://api.github.com/users/Mwaldemar",
            "html_url": "https://github.com/Mwaldemar",
            "followers_url": "https://api.github.com/users/Mwaldemar/followers",
            "following_url": "https://api.github.com/users/Mwaldemar/following{/other_user}",
            "gists_url": "https://api.github.com/users/Mwaldemar/gists{/gist_id}",
            "starred_url": "https://api.github.com/users/Mwaldemar/starred{/owner}{/repo}",
            "subscriptions_url": "https://api.github.com/users/Mwaldemar/subscriptions",
            "organizations_url": "https://api.github.com/users/Mwaldemar/orgs",
            "repos_url": "https://api.github.com/users/Mwaldemar/repos",
            "events_url": "https://api.github.com/users/Mwaldemar/events{/privacy}",
            "received_events_url": "https://api.github.com/users/Mwaldemar/received_events",
            "type": "User",
            "user_view_type": "public",
            "site_admin": false
          },
          "repo": {
            "id": 925695263,
            "node_id": "R_kgDONyz9Hw",
            "name": "Resume",
            "full_name": "Mwaldemar/Resume",
            "private": false,
            "owner": {
              "login": "Mwaldemar",
              "id": 102224869,
              "node_id": "U_kgDOBhfT5Q",
              "avatar_url": "https://avatars.githubusercontent.com/u/102224869?v=4",
              "gravatar_id": "",
              "url": "https://api.github.com/users/Mwaldemar",
              "html_url": "https://github.com/Mwaldemar",
              "followers_url": "https://api.github.com/users/Mwaldemar/followers",
              "following_url": "https://api.github.com/users/Mwaldemar/following{/other_user}",
              "gists_url": "https://api.github.com/users/Mwaldemar/gists{/gist_id}",
              "starred_url": "https://api.github.com/users/Mwaldemar/starred{/owner}{/repo}",
              "subscriptions_url": "https://api.github.com/users/Mwaldemar/subscriptions",
              "organizations_url": "https://api.github.com/users/Mwaldemar/orgs",
              "repos_url": "https://api.github.com/users/Mwaldemar/repos",
              "events_url": "https://api.github.com/users/Mwaldemar/events{/privacy}",
              "received_events_url": "https://api.github.com/users/Mwaldemar/received_events",
              "type": "User",
              "user_view_type": "public",
              "site_admin": false
            },
            "html_url": "https://github.com/Mwaldemar/Resume",
            "description": "Development of resume website",
            "fork": false,
            "url": "https://api.github.com/repos/Mwaldemar/Resume",
            "forks_url": "https://api.github.com/repos/Mwaldemar/Resume/forks",
            "keys_url": "https://api.github.com/repos/Mwaldemar/Resume/keys{/key_id}",
            "collaborators_url": "https://api.github.com/repos/Mwaldemar/Resume/collaborators{/collaborator}",
            "teams_url": "https://api.github.com/repos/Mwaldemar/Resume/teams",
            "hooks_url": "https://api.github.com/repos/Mwaldemar/Resume/hooks",
            "issue_events_url": "https://api.github.com/repos/Mwaldemar/Resume/issues/events{/number}",
            "events_url": "https://api.github.com/repos/Mwaldemar/Resume/events",
            "assignees_url": "https://api.github.com/repos/Mwaldemar/Resume/assignees{/user}",
            "branches_url": "https://api.github.com/repos/Mwaldemar/Resume/branches{/branch}",
            "tags_url": "https://api.github.com/repos/Mwaldemar/Resume/tags",
            "blobs_url": "https://api.github.com/repos/Mwaldemar/Resume/git/blobs{/sha}",
            "git_tags_url": "https://api.github.com/repos/Mwaldemar/Resume/git/tags{/sha}",
            "git_refs_url": "https://api.github.com/repos/Mwaldemar/Resume/git/refs{/sha}",
            "trees_url": "https://api.github.com/repos/Mwaldemar/Resume/git/trees{/sha}",
            "statuses_url": "https://api.github.com/repos/Mwaldemar/Resume/statuses/{sha}",
            "languages_url": "https://api.github.com/repos/Mwaldemar/Resume/languages",
            "stargazers_url": "https://api.github.com/repos/Mwaldemar/Resume/stargazers",
            "contributors_url": "https://api.github.com/repos/Mwaldemar/Resume/contributors",
            "subscribers_url": "https://api.github.com/repos/Mwaldemar/Resume/subscribers",
            "subscription_url": "https://api.github.com/repos/Mwaldemar/Resume/subscription",
            "commits_url": "https://api.github.com/repos/Mwaldemar/Resume/commits{/sha}",
            "git_commits_url": "https://api.github.com/repos/Mwaldemar/Resume/git/commits{/sha}",
            "comments_url": "https://api.github.com/repos/Mwaldemar/Resume/comments{/number}",
            "issue_comment_url": "https://api.github.com/repos/Mwaldemar/Resume/issues/comments{/number}",
            "contents_url": "https://api.github.com/repos/Mwaldemar/Resume/contents/{+path}",
            "compare_url": "https://api.github.com/repos/Mwaldemar/Resume/compare/{base}...{head}",
            "merges_url": "https://api.github.com/repos/Mwaldemar/Resume/merges",
            "archive_url": "https://api.github.com/repos/Mwaldemar/Resume/{archive_format}{/ref}",
            "downloads_url": "https://api.github.com/repos/Mwaldemar/Resume/downloads",
            "issues_url": "https://api.github.com/repos/Mwaldemar/Resume/issues{/number}",
            "pulls_url": "https://api.github.com/repos/Mwaldemar/Resume/pulls{/number}",
            "milestones_url": "https://api.github.com/repos/Mwaldemar/Resume/milestones{/number}",
            "notifications_url": "https://api.github.com/repos/Mwaldemar/Resume/notifications{?since,all,participating}",
            "labels_url": "https://api.github.com/repos/Mwaldemar/Resume/labels{/name}",
            "releases_url": "https://api.github.com/repos/Mwaldemar/Resume/releases{/id}",
            "deployments_url": "https://api.github.com/repos/Mwaldemar/Resume/deployments",
            "created_at": "2025-02-01T14:15:49Z",
            "updated_at": "2025-02-20T13:12:29Z",
            "pushed_at": "2025-02-20T13:22:35Z",
            "git_url": "git://github.com/Mwaldemar/Resume.git",
            "ssh_url": "git@github.com:Mwaldemar/Resume.git",
            "clone_url": "https://github.com/Mwaldemar/Resume.git",
            "svn_url": "https://github.com/Mwaldemar/Resume",
            "homepage": "https://resume-ruby-ten-65.vercel.app",
            "size": 1446,
            "stargazers_count": 0,
            "watchers_count": 0,
            "language": "TypeScript",
            "has_issues": true,
            "has_projects": true,
            "has_downloads": true,
            "has_wiki": true,
            "has_pages": false,
            "has_discussions": false,
            "forks_count": 0,
            "mirror_url": null,
            "archived": false,
            "disabled": false,
            "open_issues_count": 1,
            "license": null,
            "allow_forking": true,
            "is_template": false,
            "web_commit_signoff_required": false,
            "topics": [],
            "visibility": "public",
            "forks": 0,
            "open_issues": 1,
            "watchers": 0,
            "default_branch": "main"
          }
        },
        "_links": {
          "self": {
            "href": "https://api.github.com/repos/Mwaldemar/Resume/pulls/36"
          },
          "html": {
            "href": "https://github.com/Mwaldemar/Resume/pull/36"
          },
          "issue": {
            "href": "https://api.github.com/repos/Mwaldemar/Resume/issues/36"
          },
          "comments": {
            "href": "https://api.github.com/repos/Mwaldemar/Resume/issues/36/comments"
          },
          "review_comments": {
            "href": "https://api.github.com/repos/Mwaldemar/Resume/pulls/36/comments"
          },
          "review_comment": {
            "href": "https://api.github.com/repos/Mwaldemar/Resume/pulls/comments{/number}"
          },
          "commits": {
            "href": "https://api.github.com/repos/Mwaldemar/Resume/pulls/36/commits"
          },
          "statuses": {
            "href": "https://api.github.com/repos/Mwaldemar/Resume/statuses/742ede3016aabba081c2d7f2452408fb438c2587"
          }
        },
        "author_association": "OWNER",
        "auto_merge": null,
        "active_lock_reason": null,
        "merged": false,
        "mergeable": null,
        "rebaseable": null,
        "mergeable_state": "unknown",
        "merged_by": null,
        "comments": 0,
        "review_comments": 0,
        "maintainer_can_modify": false,
        "commits": 1,
        "additions": 3,
        "deletions": 2,
        "changed_files": 1
      }
    },
    "public": true,
    "created_at": "2025-02-20T13:23:20Z"
  },
  {
    "id": "46777387372",
    "type": "CreateEvent",
    "actor": {
      "id": 102224869,
      "login": "Mwaldemar",
      "display_login": "Mwaldemar",
      "gravatar_id": "",
      "url": "https://api.github.com/users/Mwaldemar",
      "avatar_url": "https://avatars.githubusercontent.com/u/102224869?"
    },
    "repo": {
      "id": 925695263,
      "name": "Mwaldemar/Resume",
      "url": "https://api.github.com/repos/Mwaldemar/Resume"
    },
    "payload": {
      "ref": "timezoneFix2",
      "ref_type": "branch",
      "master_branch": "main",
      "description": "Development of resume website",
      "pusher_type": "user"
    },
    "public": true,
    "created_at": "2025-02-20T13:22:36Z"
  },
  {
    "id": "46776970027",
    "type": "PushEvent",
    "actor": {
      "id": 102224869,
      "login": "Mwaldemar",
      "display_login": "Mwaldemar",
      "gravatar_id": "",
      "url": "https://api.github.com/users/Mwaldemar",
      "avatar_url": "https://avatars.githubusercontent.com/u/102224869?"
    },
    "repo": {
      "id": 925695263,
      "name": "Mwaldemar/Resume",
      "url": "https://api.github.com/repos/Mwaldemar/Resume"
    },
    "payload": {
      "repository_id": 925695263,
      "push_id": 22764095582,
      "size": 1,
      "distinct_size": 1,
      "ref": "refs/heads/main",
      "head": "e2a415529d573bdf49ef29c49498d8d240123734",
      "before": "c0fc8928e4b84fca696c74364fd63d45c8710901",
      "commits": [
        {
          "sha": "e2a415529d573bdf49ef29c49498d8d240123734",
          "author": {
            "email": "github-actions@github.com",
            "name": "GitHub Actions"
          },
          "message": "Update GitHub repositories",
          "distinct": true,
          "url": "https://api.github.com/repos/Mwaldemar/Resume/commits/e2a415529d573bdf49ef29c49498d8d240123734"
        }
      ]
    },
    "public": true,
    "created_at": "2025-02-20T13:12:27Z"
  },
  {
    "id": "46776923412",
    "type": "PushEvent",
    "actor": {
      "id": 102224869,
      "login": "Mwaldemar",
      "display_login": "Mwaldemar",
      "gravatar_id": "",
      "url": "https://api.github.com/users/Mwaldemar",
      "avatar_url": "https://avatars.githubusercontent.com/u/102224869?"
    },
    "repo": {
      "id": 925695263,
      "name": "Mwaldemar/Resume",
      "url": "https://api.github.com/repos/Mwaldemar/Resume"
    },
    "payload": {
      "repository_id": 925695263,
      "push_id": 22764071651,
      "size": 2,
      "distinct_size": 1,
      "ref": "refs/heads/main",
      "head": "c0fc8928e4b84fca696c74364fd63d45c8710901",
      "before": "dca7a676d5e667c0f0920188083bc4897043ee3c",
      "commits": [
        {
          "sha": "8075349dbfb6430de3d1ef032ba3448696ccd81e",
          "author": {
            "email": "304837@via.dk",
            "name": "Mwaldemar"
          },
          "message": "fixed small timezone mistake",
          "distinct": false,
          "url": "https://api.github.com/repos/Mwaldemar/Resume/commits/8075349dbfb6430de3d1ef032ba3448696ccd81e"
        },
        {
          "sha": "c0fc8928e4b84fca696c74364fd63d45c8710901",
          "author": {
            "email": "102224869+Mwaldemar@users.noreply.github.com",
            "name": "Mikkel W. Johannessen"
          },
          "message": "Merge pull request #35 from Mwaldemar/timezoneFix\n\nfixed small timezone mistake",
          "distinct": true,
          "url": "https://api.github.com/repos/Mwaldemar/Resume/commits/c0fc8928e4b84fca696c74364fd63d45c8710901"
        }
      ]
    },
    "public": true,
    "created_at": "2025-02-20T13:11:19Z"
  },
  {
    "id": "46776922744",
    "type": "PullRequestEvent",
    "actor": {
      "id": 102224869,
      "login": "Mwaldemar",
      "display_login": "Mwaldemar",
      "gravatar_id": "",
      "url": "https://api.github.com/users/Mwaldemar",
      "avatar_url": "https://avatars.githubusercontent.com/u/102224869?"
    },
    "repo": {
      "id": 925695263,
      "name": "Mwaldemar/Resume",
      "url": "https://api.github.com/repos/Mwaldemar/Resume"
    },
    "payload": {
      "action": "closed",
      "number": 35,
      "pull_request": {
        "url": "https://api.github.com/repos/Mwaldemar/Resume/pulls/35",
        "id": 2347077576,
        "node_id": "PR_kwDONyz9H86L5Y_I",
        "html_url": "https://github.com/Mwaldemar/Resume/pull/35",
        "diff_url": "https://github.com/Mwaldemar/Resume/pull/35.diff",
        "patch_url": "https://github.com/Mwaldemar/Resume/pull/35.patch",
        "issue_url": "https://api.github.com/repos/Mwaldemar/Resume/issues/35",
        "number": 35,
        "state": "closed",
        "locked": false,
        "title": "fixed small timezone mistake",
        "user": {
          "login": "Mwaldemar",
          "id": 102224869,
          "node_id": "U_kgDOBhfT5Q",
          "avatar_url": "https://avatars.githubusercontent.com/u/102224869?v=4",
          "gravatar_id": "",
          "url": "https://api.github.com/users/Mwaldemar",
          "html_url": "https://github.com/Mwaldemar",
          "followers_url": "https://api.github.com/users/Mwaldemar/followers",
          "following_url": "https://api.github.com/users/Mwaldemar/following{/other_user}",
          "gists_url": "https://api.github.com/users/Mwaldemar/gists{/gist_id}",
          "starred_url": "https://api.github.com/users/Mwaldemar/starred{/owner}{/repo}",
          "subscriptions_url": "https://api.github.com/users/Mwaldemar/subscriptions",
          "organizations_url": "https://api.github.com/users/Mwaldemar/orgs",
          "repos_url": "https://api.github.com/users/Mwaldemar/repos",
          "events_url": "https://api.github.com/users/Mwaldemar/events{/privacy}",
          "received_events_url": "https://api.github.com/users/Mwaldemar/received_events",
          "type": "User",
          "user_view_type": "public",
          "site_admin": false
        },
        "body": null,
        "created_at": "2025-02-20T13:11:10Z",
        "updated_at": "2025-02-20T13:11:17Z",
        "closed_at": "2025-02-20T13:11:17Z",
        "merged_at": "2025-02-20T13:11:17Z",
        "merge_commit_sha": "c0fc8928e4b84fca696c74364fd63d45c8710901",
        "assignee": null,
        "assignees": [],
        "requested_reviewers": [],
        "requested_teams": [],
        "labels": [],
        "milestone": null,
        "draft": false,
        "commits_url": "https://api.github.com/repos/Mwaldemar/Resume/pulls/35/commits",
        "review_comments_url": "https://api.github.com/repos/Mwaldemar/Resume/pulls/35/comments",
        "review_comment_url": "https://api.github.com/repos/Mwaldemar/Resume/pulls/comments{/number}",
        "comments_url": "https://api.github.com/repos/Mwaldemar/Resume/issues/35/comments",
        "statuses_url": "https://api.github.com/repos/Mwaldemar/Resume/statuses/8075349dbfb6430de3d1ef032ba3448696ccd81e",
        "head": {
          "label": "Mwaldemar:timezoneFix",
          "ref": "timezoneFix",
          "sha": "8075349dbfb6430de3d1ef032ba3448696ccd81e",
          "user": {
            "login": "Mwaldemar",
            "id": 102224869,
            "node_id": "U_kgDOBhfT5Q",
            "avatar_url": "https://avatars.githubusercontent.com/u/102224869?v=4",
            "gravatar_id": "",
            "url": "https://api.github.com/users/Mwaldemar",
            "html_url": "https://github.com/Mwaldemar",
            "followers_url": "https://api.github.com/users/Mwaldemar/followers",
            "following_url": "https://api.github.com/users/Mwaldemar/following{/other_user}",
            "gists_url": "https://api.github.com/users/Mwaldemar/gists{/gist_id}",
            "starred_url": "https://api.github.com/users/Mwaldemar/starred{/owner}{/repo}",
            "subscriptions_url": "https://api.github.com/users/Mwaldemar/subscriptions",
            "organizations_url": "https://api.github.com/users/Mwaldemar/orgs",
            "repos_url": "https://api.github.com/users/Mwaldemar/repos",
            "events_url": "https://api.github.com/users/Mwaldemar/events{/privacy}",
            "received_events_url": "https://api.github.com/users/Mwaldemar/received_events",
            "type": "User",
            "user_view_type": "public",
            "site_admin": false
          },
          "repo": {
            "id": 925695263,
            "node_id": "R_kgDONyz9Hw",
            "name": "Resume",
            "full_name": "Mwaldemar/Resume",
            "private": false,
            "owner": {
              "login": "Mwaldemar",
              "id": 102224869,
              "node_id": "U_kgDOBhfT5Q",
              "avatar_url": "https://avatars.githubusercontent.com/u/102224869?v=4",
              "gravatar_id": "",
              "url": "https://api.github.com/users/Mwaldemar",
              "html_url": "https://github.com/Mwaldemar",
              "followers_url": "https://api.github.com/users/Mwaldemar/followers",
              "following_url": "https://api.github.com/users/Mwaldemar/following{/other_user}",
              "gists_url": "https://api.github.com/users/Mwaldemar/gists{/gist_id}",
              "starred_url": "https://api.github.com/users/Mwaldemar/starred{/owner}{/repo}",
              "subscriptions_url": "https://api.github.com/users/Mwaldemar/subscriptions",
              "organizations_url": "https://api.github.com/users/Mwaldemar/orgs",
              "repos_url": "https://api.github.com/users/Mwaldemar/repos",
              "events_url": "https://api.github.com/users/Mwaldemar/events{/privacy}",
              "received_events_url": "https://api.github.com/users/Mwaldemar/received_events",
              "type": "User",
              "user_view_type": "public",
              "site_admin": false
            },
            "html_url": "https://github.com/Mwaldemar/Resume",
            "description": "Development of resume website",
            "fork": false,
            "url": "https://api.github.com/repos/Mwaldemar/Resume",
            "forks_url": "https://api.github.com/repos/Mwaldemar/Resume/forks",
            "keys_url": "https://api.github.com/repos/Mwaldemar/Resume/keys{/key_id}",
            "collaborators_url": "https://api.github.com/repos/Mwaldemar/Resume/collaborators{/collaborator}",
            "teams_url": "https://api.github.com/repos/Mwaldemar/Resume/teams",
            "hooks_url": "https://api.github.com/repos/Mwaldemar/Resume/hooks",
            "issue_events_url": "https://api.github.com/repos/Mwaldemar/Resume/issues/events{/number}",
            "events_url": "https://api.github.com/repos/Mwaldemar/Resume/events",
            "assignees_url": "https://api.github.com/repos/Mwaldemar/Resume/assignees{/user}",
            "branches_url": "https://api.github.com/repos/Mwaldemar/Resume/branches{/branch}",
            "tags_url": "https://api.github.com/repos/Mwaldemar/Resume/tags",
            "blobs_url": "https://api.github.com/repos/Mwaldemar/Resume/git/blobs{/sha}",
            "git_tags_url": "https://api.github.com/repos/Mwaldemar/Resume/git/tags{/sha}",
            "git_refs_url": "https://api.github.com/repos/Mwaldemar/Resume/git/refs{/sha}",
            "trees_url": "https://api.github.com/repos/Mwaldemar/Resume/git/trees{/sha}",
            "statuses_url": "https://api.github.com/repos/Mwaldemar/Resume/statuses/{sha}",
            "languages_url": "https://api.github.com/repos/Mwaldemar/Resume/languages",
            "stargazers_url": "https://api.github.com/repos/Mwaldemar/Resume/stargazers",
            "contributors_url": "https://api.github.com/repos/Mwaldemar/Resume/contributors",
            "subscribers_url": "https://api.github.com/repos/Mwaldemar/Resume/subscribers",
            "subscription_url": "https://api.github.com/repos/Mwaldemar/Resume/subscription",
            "commits_url": "https://api.github.com/repos/Mwaldemar/Resume/commits{/sha}",
            "git_commits_url": "https://api.github.com/repos/Mwaldemar/Resume/git/commits{/sha}",
            "comments_url": "https://api.github.com/repos/Mwaldemar/Resume/comments{/number}",
            "issue_comment_url": "https://api.github.com/repos/Mwaldemar/Resume/issues/comments{/number}",
            "contents_url": "https://api.github.com/repos/Mwaldemar/Resume/contents/{+path}",
            "compare_url": "https://api.github.com/repos/Mwaldemar/Resume/compare/{base}...{head}",
            "merges_url": "https://api.github.com/repos/Mwaldemar/Resume/merges",
            "archive_url": "https://api.github.com/repos/Mwaldemar/Resume/{archive_format}{/ref}",
            "downloads_url": "https://api.github.com/repos/Mwaldemar/Resume/downloads",
            "issues_url": "https://api.github.com/repos/Mwaldemar/Resume/issues{/number}",
            "pulls_url": "https://api.github.com/repos/Mwaldemar/Resume/pulls{/number}",
            "milestones_url": "https://api.github.com/repos/Mwaldemar/Resume/milestones{/number}",
            "notifications_url": "https://api.github.com/repos/Mwaldemar/Resume/notifications{?since,all,participating}",
            "labels_url": "https://api.github.com/repos/Mwaldemar/Resume/labels{/name}",
            "releases_url": "https://api.github.com/repos/Mwaldemar/Resume/releases{/id}",
            "deployments_url": "https://api.github.com/repos/Mwaldemar/Resume/deployments",
            "created_at": "2025-02-01T14:15:49Z",
            "updated_at": "2025-02-20T13:05:35Z",
            "pushed_at": "2025-02-20T13:10:59Z",
            "git_url": "git://github.com/Mwaldemar/Resume.git",
            "ssh_url": "git@github.com:Mwaldemar/Resume.git",
            "clone_url": "https://github.com/Mwaldemar/Resume.git",
            "svn_url": "https://github.com/Mwaldemar/Resume",
            "homepage": "https://resume-ruby-ten-65.vercel.app",
            "size": 1446,
            "stargazers_count": 0,
            "watchers_count": 0,
            "language": "TypeScript",
            "has_issues": true,
            "has_projects": true,
            "has_downloads": true,
            "has_wiki": true,
            "has_pages": false,
            "has_discussions": false,
            "forks_count": 0,
            "mirror_url": null,
            "archived": false,
            "disabled": false,
            "open_issues_count": 0,
            "license": null,
            "allow_forking": true,
            "is_template": false,
            "web_commit_signoff_required": false,
            "topics": [],
            "visibility": "public",
            "forks": 0,
            "open_issues": 0,
            "watchers": 0,
            "default_branch": "main"
          }
        },
        "base": {
          "label": "Mwaldemar:main",
          "ref": "main",
          "sha": "dca7a676d5e667c0f0920188083bc4897043ee3c",
          "user": {
            "login": "Mwaldemar",
            "id": 102224869,
            "node_id": "U_kgDOBhfT5Q",
            "avatar_url": "https://avatars.githubusercontent.com/u/102224869?v=4",
            "gravatar_id": "",
            "url": "https://api.github.com/users/Mwaldemar",
            "html_url": "https://github.com/Mwaldemar",
            "followers_url": "https://api.github.com/users/Mwaldemar/followers",
            "following_url": "https://api.github.com/users/Mwaldemar/following{/other_user}",
            "gists_url": "https://api.github.com/users/Mwaldemar/gists{/gist_id}",
            "starred_url": "https://api.github.com/users/Mwaldemar/starred{/owner}{/repo}",
            "subscriptions_url": "https://api.github.com/users/Mwaldemar/subscriptions",
            "organizations_url": "https://api.github.com/users/Mwaldemar/orgs",
            "repos_url": "https://api.github.com/users/Mwaldemar/repos",
            "events_url": "https://api.github.com/users/Mwaldemar/events{/privacy}",
            "received_events_url": "https://api.github.com/users/Mwaldemar/received_events",
            "type": "User",
            "user_view_type": "public",
            "site_admin": false
          },
          "repo": {
            "id": 925695263,
            "node_id": "R_kgDONyz9Hw",
            "name": "Resume",
            "full_name": "Mwaldemar/Resume",
            "private": false,
            "owner": {
              "login": "Mwaldemar",
              "id": 102224869,
              "node_id": "U_kgDOBhfT5Q",
              "avatar_url": "https://avatars.githubusercontent.com/u/102224869?v=4",
              "gravatar_id": "",
              "url": "https://api.github.com/users/Mwaldemar",
              "html_url": "https://github.com/Mwaldemar",
              "followers_url": "https://api.github.com/users/Mwaldemar/followers",
              "following_url": "https://api.github.com/users/Mwaldemar/following{/other_user}",
              "gists_url": "https://api.github.com/users/Mwaldemar/gists{/gist_id}",
              "starred_url": "https://api.github.com/users/Mwaldemar/starred{/owner}{/repo}",
              "subscriptions_url": "https://api.github.com/users/Mwaldemar/subscriptions",
              "organizations_url": "https://api.github.com/users/Mwaldemar/orgs",
              "repos_url": "https://api.github.com/users/Mwaldemar/repos",
              "events_url": "https://api.github.com/users/Mwaldemar/events{/privacy}",
              "received_events_url": "https://api.github.com/users/Mwaldemar/received_events",
              "type": "User",
              "user_view_type": "public",
              "site_admin": false
            },
            "html_url": "https://github.com/Mwaldemar/Resume",
            "description": "Development of resume website",
            "fork": false,
            "url": "https://api.github.com/repos/Mwaldemar/Resume",
            "forks_url": "https://api.github.com/repos/Mwaldemar/Resume/forks",
            "keys_url": "https://api.github.com/repos/Mwaldemar/Resume/keys{/key_id}",
            "collaborators_url": "https://api.github.com/repos/Mwaldemar/Resume/collaborators{/collaborator}",
            "teams_url": "https://api.github.com/repos/Mwaldemar/Resume/teams",
            "hooks_url": "https://api.github.com/repos/Mwaldemar/Resume/hooks",
            "issue_events_url": "https://api.github.com/repos/Mwaldemar/Resume/issues/events{/number}",
            "events_url": "https://api.github.com/repos/Mwaldemar/Resume/events",
            "assignees_url": "https://api.github.com/repos/Mwaldemar/Resume/assignees{/user}",
            "branches_url": "https://api.github.com/repos/Mwaldemar/Resume/branches{/branch}",
            "tags_url": "https://api.github.com/repos/Mwaldemar/Resume/tags",
            "blobs_url": "https://api.github.com/repos/Mwaldemar/Resume/git/blobs{/sha}",
            "git_tags_url": "https://api.github.com/repos/Mwaldemar/Resume/git/tags{/sha}",
            "git_refs_url": "https://api.github.com/repos/Mwaldemar/Resume/git/refs{/sha}",
            "trees_url": "https://api.github.com/repos/Mwaldemar/Resume/git/trees{/sha}",
            "statuses_url": "https://api.github.com/repos/Mwaldemar/Resume/statuses/{sha}",
            "languages_url": "https://api.github.com/repos/Mwaldemar/Resume/languages",
            "stargazers_url": "https://api.github.com/repos/Mwaldemar/Resume/stargazers",
            "contributors_url": "https://api.github.com/repos/Mwaldemar/Resume/contributors",
            "subscribers_url": "https://api.github.com/repos/Mwaldemar/Resume/subscribers",
            "subscription_url": "https://api.github.com/repos/Mwaldemar/Resume/subscription",
            "commits_url": "https://api.github.com/repos/Mwaldemar/Resume/commits{/sha}",
            "git_commits_url": "https://api.github.com/repos/Mwaldemar/Resume/git/commits{/sha}",
            "comments_url": "https://api.github.com/repos/Mwaldemar/Resume/comments{/number}",
            "issue_comment_url": "https://api.github.com/repos/Mwaldemar/Resume/issues/comments{/number}",
            "contents_url": "https://api.github.com/repos/Mwaldemar/Resume/contents/{+path}",
            "compare_url": "https://api.github.com/repos/Mwaldemar/Resume/compare/{base}...{head}",
            "merges_url": "https://api.github.com/repos/Mwaldemar/Resume/merges",
            "archive_url": "https://api.github.com/repos/Mwaldemar/Resume/{archive_format}{/ref}",
            "downloads_url": "https://api.github.com/repos/Mwaldemar/Resume/downloads",
            "issues_url": "https://api.github.com/repos/Mwaldemar/Resume/issues{/number}",
            "pulls_url": "https://api.github.com/repos/Mwaldemar/Resume/pulls{/number}",
            "milestones_url": "https://api.github.com/repos/Mwaldemar/Resume/milestones{/number}",
            "notifications_url": "https://api.github.com/repos/Mwaldemar/Resume/notifications{?since,all,participating}",
            "labels_url": "https://api.github.com/repos/Mwaldemar/Resume/labels{/name}",
            "releases_url": "https://api.github.com/repos/Mwaldemar/Resume/releases{/id}",
            "deployments_url": "https://api.github.com/repos/Mwaldemar/Resume/deployments",
            "created_at": "2025-02-01T14:15:49Z",
            "updated_at": "2025-02-20T13:05:35Z",
            "pushed_at": "2025-02-20T13:10:59Z",
            "git_url": "git://github.com/Mwaldemar/Resume.git",
            "ssh_url": "git@github.com:Mwaldemar/Resume.git",
            "clone_url": "https://github.com/Mwaldemar/Resume.git",
            "svn_url": "https://github.com/Mwaldemar/Resume",
            "homepage": "https://resume-ruby-ten-65.vercel.app",
            "size": 1446,
            "stargazers_count": 0,
            "watchers_count": 0,
            "language": "TypeScript",
            "has_issues": true,
            "has_projects": true,
            "has_downloads": true,
            "has_wiki": true,
            "has_pages": false,
            "has_discussions": false,
            "forks_count": 0,
            "mirror_url": null,
            "archived": false,
            "disabled": false,
            "open_issues_count": 0,
            "license": null,
            "allow_forking": true,
            "is_template": false,
            "web_commit_signoff_required": false,
            "topics": [],
            "visibility": "public",
            "forks": 0,
            "open_issues": 0,
            "watchers": 0,
            "default_branch": "main"
          }
        },
        "_links": {
          "self": {
            "href": "https://api.github.com/repos/Mwaldemar/Resume/pulls/35"
          },
          "html": {
            "href": "https://github.com/Mwaldemar/Resume/pull/35"
          },
          "issue": {
            "href": "https://api.github.com/repos/Mwaldemar/Resume/issues/35"
          },
          "comments": {
            "href": "https://api.github.com/repos/Mwaldemar/Resume/issues/35/comments"
          },
          "review_comments": {
            "href": "https://api.github.com/repos/Mwaldemar/Resume/pulls/35/comments"
          },
          "review_comment": {
            "href": "https://api.github.com/repos/Mwaldemar/Resume/pulls/comments{/number}"
          },
          "commits": {
            "href": "https://api.github.com/repos/Mwaldemar/Resume/pulls/35/commits"
          },
          "statuses": {
            "href": "https://api.github.com/repos/Mwaldemar/Resume/statuses/8075349dbfb6430de3d1ef032ba3448696ccd81e"
          }
        },
        "author_association": "OWNER",
        "auto_merge": null,
        "active_lock_reason": null,
        "merged": true,
        "mergeable": null,
        "rebaseable": null,
        "mergeable_state": "unknown",
        "merged_by": {
          "login": "Mwaldemar",
          "id": 102224869,
          "node_id": "U_kgDOBhfT5Q",
          "avatar_url": "https://avatars.githubusercontent.com/u/102224869?v=4",
          "gravatar_id": "",
          "url": "https://api.github.com/users/Mwaldemar",
          "html_url": "https://github.com/Mwaldemar",
          "followers_url": "https://api.github.com/users/Mwaldemar/followers",
          "following_url": "https://api.github.com/users/Mwaldemar/following{/other_user}",
          "gists_url": "https://api.github.com/users/Mwaldemar/gists{/gist_id}",
          "starred_url": "https://api.github.com/users/Mwaldemar/starred{/owner}{/repo}",
          "subscriptions_url": "https://api.github.com/users/Mwaldemar/subscriptions",
          "organizations_url": "https://api.github.com/users/Mwaldemar/orgs",
          "repos_url": "https://api.github.com/users/Mwaldemar/repos",
          "events_url": "https://api.github.com/users/Mwaldemar/events{/privacy}",
          "received_events_url": "https://api.github.com/users/Mwaldemar/received_events",
          "type": "User",
          "user_view_type": "public",
          "site_admin": false
        },
        "comments": 1,
        "review_comments": 0,
        "maintainer_can_modify": false,
        "commits": 1,
        "additions": 1,
        "deletions": 1,
        "changed_files": 1
      }
    },
    "public": true,
    "created_at": "2025-02-20T13:11:18Z"
  },
  {
    "id": "46776919295",
    "type": "PullRequestEvent",
    "actor": {
      "id": 102224869,
      "login": "Mwaldemar",
      "display_login": "Mwaldemar",
      "gravatar_id": "",
      "url": "https://api.github.com/users/Mwaldemar",
      "avatar_url": "https://avatars.githubusercontent.com/u/102224869?"
    },
    "repo": {
      "id": 925695263,
      "name": "Mwaldemar/Resume",
      "url": "https://api.github.com/repos/Mwaldemar/Resume"
    },
    "payload": {
      "action": "opened",
      "number": 35,
      "pull_request": {
        "url": "https://api.github.com/repos/Mwaldemar/Resume/pulls/35",
        "id": 2347077576,
        "node_id": "PR_kwDONyz9H86L5Y_I",
        "html_url": "https://github.com/Mwaldemar/Resume/pull/35",
        "diff_url": "https://github.com/Mwaldemar/Resume/pull/35.diff",
        "patch_url": "https://github.com/Mwaldemar/Resume/pull/35.patch",
        "issue_url": "https://api.github.com/repos/Mwaldemar/Resume/issues/35",
        "number": 35,
        "state": "open",
        "locked": false,
        "title": "fixed small timezone mistake",
        "user": {
          "login": "Mwaldemar",
          "id": 102224869,
          "node_id": "U_kgDOBhfT5Q",
          "avatar_url": "https://avatars.githubusercontent.com/u/102224869?v=4",
          "gravatar_id": "",
          "url": "https://api.github.com/users/Mwaldemar",
          "html_url": "https://github.com/Mwaldemar",
          "followers_url": "https://api.github.com/users/Mwaldemar/followers",
          "following_url": "https://api.github.com/users/Mwaldemar/following{/other_user}",
          "gists_url": "https://api.github.com/users/Mwaldemar/gists{/gist_id}",
          "starred_url": "https://api.github.com/users/Mwaldemar/starred{/owner}{/repo}",
          "subscriptions_url": "https://api.github.com/users/Mwaldemar/subscriptions",
          "organizations_url": "https://api.github.com/users/Mwaldemar/orgs",
          "repos_url": "https://api.github.com/users/Mwaldemar/repos",
          "events_url": "https://api.github.com/users/Mwaldemar/events{/privacy}",
          "received_events_url": "https://api.github.com/users/Mwaldemar/received_events",
          "type": "User",
          "user_view_type": "public",
          "site_admin": false
        },
        "body": null,
        "created_at": "2025-02-20T13:11:10Z",
        "updated_at": "2025-02-20T13:11:10Z",
        "closed_at": null,
        "merged_at": null,
        "merge_commit_sha": null,
        "assignee": null,
        "assignees": [],
        "requested_reviewers": [],
        "requested_teams": [],
        "labels": [],
        "milestone": null,
        "draft": false,
        "commits_url": "https://api.github.com/repos/Mwaldemar/Resume/pulls/35/commits",
        "review_comments_url": "https://api.github.com/repos/Mwaldemar/Resume/pulls/35/comments",
        "review_comment_url": "https://api.github.com/repos/Mwaldemar/Resume/pulls/comments{/number}",
        "comments_url": "https://api.github.com/repos/Mwaldemar/Resume/issues/35/comments",
        "statuses_url": "https://api.github.com/repos/Mwaldemar/Resume/statuses/8075349dbfb6430de3d1ef032ba3448696ccd81e",
        "head": {
          "label": "Mwaldemar:timezoneFix",
          "ref": "timezoneFix",
          "sha": "8075349dbfb6430de3d1ef032ba3448696ccd81e",
          "user": {
            "login": "Mwaldemar",
            "id": 102224869,
            "node_id": "U_kgDOBhfT5Q",
            "avatar_url": "https://avatars.githubusercontent.com/u/102224869?v=4",
            "gravatar_id": "",
            "url": "https://api.github.com/users/Mwaldemar",
            "html_url": "https://github.com/Mwaldemar",
            "followers_url": "https://api.github.com/users/Mwaldemar/followers",
            "following_url": "https://api.github.com/users/Mwaldemar/following{/other_user}",
            "gists_url": "https://api.github.com/users/Mwaldemar/gists{/gist_id}",
            "starred_url": "https://api.github.com/users/Mwaldemar/starred{/owner}{/repo}",
            "subscriptions_url": "https://api.github.com/users/Mwaldemar/subscriptions",
            "organizations_url": "https://api.github.com/users/Mwaldemar/orgs",
            "repos_url": "https://api.github.com/users/Mwaldemar/repos",
            "events_url": "https://api.github.com/users/Mwaldemar/events{/privacy}",
            "received_events_url": "https://api.github.com/users/Mwaldemar/received_events",
            "type": "User",
            "user_view_type": "public",
            "site_admin": false
          },
          "repo": {
            "id": 925695263,
            "node_id": "R_kgDONyz9Hw",
            "name": "Resume",
            "full_name": "Mwaldemar/Resume",
            "private": false,
            "owner": {
              "login": "Mwaldemar",
              "id": 102224869,
              "node_id": "U_kgDOBhfT5Q",
              "avatar_url": "https://avatars.githubusercontent.com/u/102224869?v=4",
              "gravatar_id": "",
              "url": "https://api.github.com/users/Mwaldemar",
              "html_url": "https://github.com/Mwaldemar",
              "followers_url": "https://api.github.com/users/Mwaldemar/followers",
              "following_url": "https://api.github.com/users/Mwaldemar/following{/other_user}",
              "gists_url": "https://api.github.com/users/Mwaldemar/gists{/gist_id}",
              "starred_url": "https://api.github.com/users/Mwaldemar/starred{/owner}{/repo}",
              "subscriptions_url": "https://api.github.com/users/Mwaldemar/subscriptions",
              "organizations_url": "https://api.github.com/users/Mwaldemar/orgs",
              "repos_url": "https://api.github.com/users/Mwaldemar/repos",
              "events_url": "https://api.github.com/users/Mwaldemar/events{/privacy}",
              "received_events_url": "https://api.github.com/users/Mwaldemar/received_events",
              "type": "User",
              "user_view_type": "public",
              "site_admin": false
            },
            "html_url": "https://github.com/Mwaldemar/Resume",
            "description": "Development of resume website",
            "fork": false,
            "url": "https://api.github.com/repos/Mwaldemar/Resume",
            "forks_url": "https://api.github.com/repos/Mwaldemar/Resume/forks",
            "keys_url": "https://api.github.com/repos/Mwaldemar/Resume/keys{/key_id}",
            "collaborators_url": "https://api.github.com/repos/Mwaldemar/Resume/collaborators{/collaborator}",
            "teams_url": "https://api.github.com/repos/Mwaldemar/Resume/teams",
            "hooks_url": "https://api.github.com/repos/Mwaldemar/Resume/hooks",
            "issue_events_url": "https://api.github.com/repos/Mwaldemar/Resume/issues/events{/number}",
            "events_url": "https://api.github.com/repos/Mwaldemar/Resume/events",
            "assignees_url": "https://api.github.com/repos/Mwaldemar/Resume/assignees{/user}",
            "branches_url": "https://api.github.com/repos/Mwaldemar/Resume/branches{/branch}",
            "tags_url": "https://api.github.com/repos/Mwaldemar/Resume/tags",
            "blobs_url": "https://api.github.com/repos/Mwaldemar/Resume/git/blobs{/sha}",
            "git_tags_url": "https://api.github.com/repos/Mwaldemar/Resume/git/tags{/sha}",
            "git_refs_url": "https://api.github.com/repos/Mwaldemar/Resume/git/refs{/sha}",
            "trees_url": "https://api.github.com/repos/Mwaldemar/Resume/git/trees{/sha}",
            "statuses_url": "https://api.github.com/repos/Mwaldemar/Resume/statuses/{sha}",
            "languages_url": "https://api.github.com/repos/Mwaldemar/Resume/languages",
            "stargazers_url": "https://api.github.com/repos/Mwaldemar/Resume/stargazers",
            "contributors_url": "https://api.github.com/repos/Mwaldemar/Resume/contributors",
            "subscribers_url": "https://api.github.com/repos/Mwaldemar/Resume/subscribers",
            "subscription_url": "https://api.github.com/repos/Mwaldemar/Resume/subscription",
            "commits_url": "https://api.github.com/repos/Mwaldemar/Resume/commits{/sha}",
            "git_commits_url": "https://api.github.com/repos/Mwaldemar/Resume/git/commits{/sha}",
            "comments_url": "https://api.github.com/repos/Mwaldemar/Resume/comments{/number}",
            "issue_comment_url": "https://api.github.com/repos/Mwaldemar/Resume/issues/comments{/number}",
            "contents_url": "https://api.github.com/repos/Mwaldemar/Resume/contents/{+path}",
            "compare_url": "https://api.github.com/repos/Mwaldemar/Resume/compare/{base}...{head}",
            "merges_url": "https://api.github.com/repos/Mwaldemar/Resume/merges",
            "archive_url": "https://api.github.com/repos/Mwaldemar/Resume/{archive_format}{/ref}",
            "downloads_url": "https://api.github.com/repos/Mwaldemar/Resume/downloads",
            "issues_url": "https://api.github.com/repos/Mwaldemar/Resume/issues{/number}",
            "pulls_url": "https://api.github.com/repos/Mwaldemar/Resume/pulls{/number}",
            "milestones_url": "https://api.github.com/repos/Mwaldemar/Resume/milestones{/number}",
            "notifications_url": "https://api.github.com/repos/Mwaldemar/Resume/notifications{?since,all,participating}",
            "labels_url": "https://api.github.com/repos/Mwaldemar/Resume/labels{/name}",
            "releases_url": "https://api.github.com/repos/Mwaldemar/Resume/releases{/id}",
            "deployments_url": "https://api.github.com/repos/Mwaldemar/Resume/deployments",
            "created_at": "2025-02-01T14:15:49Z",
            "updated_at": "2025-02-20T13:05:35Z",
            "pushed_at": "2025-02-20T13:10:59Z",
            "git_url": "git://github.com/Mwaldemar/Resume.git",
            "ssh_url": "git@github.com:Mwaldemar/Resume.git",
            "clone_url": "https://github.com/Mwaldemar/Resume.git",
            "svn_url": "https://github.com/Mwaldemar/Resume",
            "homepage": "https://resume-ruby-ten-65.vercel.app",
            "size": 1446,
            "stargazers_count": 0,
            "watchers_count": 0,
            "language": "TypeScript",
            "has_issues": true,
            "has_projects": true,
            "has_downloads": true,
            "has_wiki": true,
            "has_pages": false,
            "has_discussions": false,
            "forks_count": 0,
            "mirror_url": null,
            "archived": false,
            "disabled": false,
            "open_issues_count": 1,
            "license": null,
            "allow_forking": true,
            "is_template": false,
            "web_commit_signoff_required": false,
            "topics": [],
            "visibility": "public",
            "forks": 0,
            "open_issues": 1,
            "watchers": 0,
            "default_branch": "main"
          }
        },
        "base": {
          "label": "Mwaldemar:main",
          "ref": "main",
          "sha": "dca7a676d5e667c0f0920188083bc4897043ee3c",
          "user": {
            "login": "Mwaldemar",
            "id": 102224869,
            "node_id": "U_kgDOBhfT5Q",
            "avatar_url": "https://avatars.githubusercontent.com/u/102224869?v=4",
            "gravatar_id": "",
            "url": "https://api.github.com/users/Mwaldemar",
            "html_url": "https://github.com/Mwaldemar",
            "followers_url": "https://api.github.com/users/Mwaldemar/followers",
            "following_url": "https://api.github.com/users/Mwaldemar/following{/other_user}",
            "gists_url": "https://api.github.com/users/Mwaldemar/gists{/gist_id}",
            "starred_url": "https://api.github.com/users/Mwaldemar/starred{/owner}{/repo}",
            "subscriptions_url": "https://api.github.com/users/Mwaldemar/subscriptions",
            "organizations_url": "https://api.github.com/users/Mwaldemar/orgs",
            "repos_url": "https://api.github.com/users/Mwaldemar/repos",
            "events_url": "https://api.github.com/users/Mwaldemar/events{/privacy}",
            "received_events_url": "https://api.github.com/users/Mwaldemar/received_events",
            "type": "User",
            "user_view_type": "public",
            "site_admin": false
          },
          "repo": {
            "id": 925695263,
            "node_id": "R_kgDONyz9Hw",
            "name": "Resume",
            "full_name": "Mwaldemar/Resume",
            "private": false,
            "owner": {
              "login": "Mwaldemar",
              "id": 102224869,
              "node_id": "U_kgDOBhfT5Q",
              "avatar_url": "https://avatars.githubusercontent.com/u/102224869?v=4",
              "gravatar_id": "",
              "url": "https://api.github.com/users/Mwaldemar",
              "html_url": "https://github.com/Mwaldemar",
              "followers_url": "https://api.github.com/users/Mwaldemar/followers",
              "following_url": "https://api.github.com/users/Mwaldemar/following{/other_user}",
              "gists_url": "https://api.github.com/users/Mwaldemar/gists{/gist_id}",
              "starred_url": "https://api.github.com/users/Mwaldemar/starred{/owner}{/repo}",
              "subscriptions_url": "https://api.github.com/users/Mwaldemar/subscriptions",
              "organizations_url": "https://api.github.com/users/Mwaldemar/orgs",
              "repos_url": "https://api.github.com/users/Mwaldemar/repos",
              "events_url": "https://api.github.com/users/Mwaldemar/events{/privacy}",
              "received_events_url": "https://api.github.com/users/Mwaldemar/received_events",
              "type": "User",
              "user_view_type": "public",
              "site_admin": false
            },
            "html_url": "https://github.com/Mwaldemar/Resume",
            "description": "Development of resume website",
            "fork": false,
            "url": "https://api.github.com/repos/Mwaldemar/Resume",
            "forks_url": "https://api.github.com/repos/Mwaldemar/Resume/forks",
            "keys_url": "https://api.github.com/repos/Mwaldemar/Resume/keys{/key_id}",
            "collaborators_url": "https://api.github.com/repos/Mwaldemar/Resume/collaborators{/collaborator}",
            "teams_url": "https://api.github.com/repos/Mwaldemar/Resume/teams",
            "hooks_url": "https://api.github.com/repos/Mwaldemar/Resume/hooks",
            "issue_events_url": "https://api.github.com/repos/Mwaldemar/Resume/issues/events{/number}",
            "events_url": "https://api.github.com/repos/Mwaldemar/Resume/events",
            "assignees_url": "https://api.github.com/repos/Mwaldemar/Resume/assignees{/user}",
            "branches_url": "https://api.github.com/repos/Mwaldemar/Resume/branches{/branch}",
            "tags_url": "https://api.github.com/repos/Mwaldemar/Resume/tags",
            "blobs_url": "https://api.github.com/repos/Mwaldemar/Resume/git/blobs{/sha}",
            "git_tags_url": "https://api.github.com/repos/Mwaldemar/Resume/git/tags{/sha}",
            "git_refs_url": "https://api.github.com/repos/Mwaldemar/Resume/git/refs{/sha}",
            "trees_url": "https://api.github.com/repos/Mwaldemar/Resume/git/trees{/sha}",
            "statuses_url": "https://api.github.com/repos/Mwaldemar/Resume/statuses/{sha}",
            "languages_url": "https://api.github.com/repos/Mwaldemar/Resume/languages",
            "stargazers_url": "https://api.github.com/repos/Mwaldemar/Resume/stargazers",
            "contributors_url": "https://api.github.com/repos/Mwaldemar/Resume/contributors",
            "subscribers_url": "https://api.github.com/repos/Mwaldemar/Resume/subscribers",
            "subscription_url": "https://api.github.com/repos/Mwaldemar/Resume/subscription",
            "commits_url": "https://api.github.com/repos/Mwaldemar/Resume/commits{/sha}",
            "git_commits_url": "https://api.github.com/repos/Mwaldemar/Resume/git/commits{/sha}",
            "comments_url": "https://api.github.com/repos/Mwaldemar/Resume/comments{/number}",
            "issue_comment_url": "https://api.github.com/repos/Mwaldemar/Resume/issues/comments{/number}",
            "contents_url": "https://api.github.com/repos/Mwaldemar/Resume/contents/{+path}",
            "compare_url": "https://api.github.com/repos/Mwaldemar/Resume/compare/{base}...{head}",
            "merges_url": "https://api.github.com/repos/Mwaldemar/Resume/merges",
            "archive_url": "https://api.github.com/repos/Mwaldemar/Resume/{archive_format}{/ref}",
            "downloads_url": "https://api.github.com/repos/Mwaldemar/Resume/downloads",
            "issues_url": "https://api.github.com/repos/Mwaldemar/Resume/issues{/number}",
            "pulls_url": "https://api.github.com/repos/Mwaldemar/Resume/pulls{/number}",
            "milestones_url": "https://api.github.com/repos/Mwaldemar/Resume/milestones{/number}",
            "notifications_url": "https://api.github.com/repos/Mwaldemar/Resume/notifications{?since,all,participating}",
            "labels_url": "https://api.github.com/repos/Mwaldemar/Resume/labels{/name}",
            "releases_url": "https://api.github.com/repos/Mwaldemar/Resume/releases{/id}",
            "deployments_url": "https://api.github.com/repos/Mwaldemar/Resume/deployments",
            "created_at": "2025-02-01T14:15:49Z",
            "updated_at": "2025-02-20T13:05:35Z",
            "pushed_at": "2025-02-20T13:10:59Z",
            "git_url": "git://github.com/Mwaldemar/Resume.git",
            "ssh_url": "git@github.com:Mwaldemar/Resume.git",
            "clone_url": "https://github.com/Mwaldemar/Resume.git",
            "svn_url": "https://github.com/Mwaldemar/Resume",
            "homepage": "https://resume-ruby-ten-65.vercel.app",
            "size": 1446,
            "stargazers_count": 0,
            "watchers_count": 0,
            "language": "TypeScript",
            "has_issues": true,
            "has_projects": true,
            "has_downloads": true,
            "has_wiki": true,
            "has_pages": false,
            "has_discussions": false,
            "forks_count": 0,
            "mirror_url": null,
            "archived": false,
            "disabled": false,
            "open_issues_count": 1,
            "license": null,
            "allow_forking": true,
            "is_template": false,
            "web_commit_signoff_required": false,
            "topics": [],
            "visibility": "public",
            "forks": 0,
            "open_issues": 1,
            "watchers": 0,
            "default_branch": "main"
          }
        },
        "_links": {
          "self": {
            "href": "https://api.github.com/repos/Mwaldemar/Resume/pulls/35"
          },
          "html": {
            "href": "https://github.com/Mwaldemar/Resume/pull/35"
          },
          "issue": {
            "href": "https://api.github.com/repos/Mwaldemar/Resume/issues/35"
          },
          "comments": {
            "href": "https://api.github.com/repos/Mwaldemar/Resume/issues/35/comments"
          },
          "review_comments": {
            "href": "https://api.github.com/repos/Mwaldemar/Resume/pulls/35/comments"
          },
          "review_comment": {
            "href": "https://api.github.com/repos/Mwaldemar/Resume/pulls/comments{/number}"
          },
          "commits": {
            "href": "https://api.github.com/repos/Mwaldemar/Resume/pulls/35/commits"
          },
          "statuses": {
            "href": "https://api.github.com/repos/Mwaldemar/Resume/statuses/8075349dbfb6430de3d1ef032ba3448696ccd81e"
          }
        },
        "author_association": "OWNER",
        "auto_merge": null,
        "active_lock_reason": null,
        "merged": false,
        "mergeable": null,
        "rebaseable": null,
        "mergeable_state": "unknown",
        "merged_by": null,
        "comments": 0,
        "review_comments": 0,
        "maintainer_can_modify": false,
        "commits": 1,
        "additions": 1,
        "deletions": 1,
        "changed_files": 1
      }
    },
    "public": true,
    "created_at": "2025-02-20T13:11:13Z"
  },
  {
    "id": "46776911001",
    "type": "CreateEvent",
    "actor": {
      "id": 102224869,
      "login": "Mwaldemar",
      "display_login": "Mwaldemar",
      "gravatar_id": "",
      "url": "https://api.github.com/users/Mwaldemar",
      "avatar_url": "https://avatars.githubusercontent.com/u/102224869?"
    },
    "repo": {
      "id": 925695263,
      "name": "Mwaldemar/Resume",
      "url": "https://api.github.com/repos/Mwaldemar/Resume"
    },
    "payload": {
      "ref": "timezoneFix",
      "ref_type": "branch",
      "master_branch": "main",
      "description": "Development of resume website",
      "pusher_type": "user"
    },
    "public": true,
    "created_at": "2025-02-20T13:11:00Z"
  }
]